Workbook

Sheet Свод (2)
A1: Период | B1: Тип премирования | C1: Год | D1: Дата процедуры | E1: ИД сотрудника | F1: Должность | G1: Полный путь до подразделения | H1: Группа целей | I1: Наименование цели | J1: Описание цели/ожидаемый результат цели | K1: Название связанной цели/метки | L1: Тип цели | M1: Источник целей | N1: Название источника | O1: Должность из Каскад метрик_инвентаризация_28082026_ИВР
A2: 3 квартал 2026 | B2: Год + квартал | C2: 2026 | D2: 01.07.2026 - 30.09.2026 | E2: 1 | F2: Заместитель главного инженера | G2: Общество с ограниченной ответственностью "Томскнефтехим"/Направление Главного инженера/Направление заместителя главного инженера | H2: Базовые обязательства | I2: Средневзвешенная длительность реализации НБ проектов (I2I) | J2: не более 414 дней | K2: Выполнение целей стратегии устойчивого развития, % Не менее 100 % | L2: Количественная | M2: Контракт | N2: ТНХ 2026 | O2: =INDEX('список ID из СУЭ с должностями'!$A:$F,MATCH(E2,'список ID из СУЭ с должностями'!$B:$B,0),5) -> 0
A3: 3 квартал 2026 | B3: Год + квартал | C3: 2026 | D3: 01.07.2026 - 30.09.2026 | E3: 1 | F3: Заместитель главного инженера | G3: Общество с ограниченной ответственностью "Томскнефтехим"/Направление Главного инженера/Направление заместителя главного инженера | H3: Задачи с эффектом в текущем году | I3: Реализация проектов | J3: 1. «Тех.перевооружение: Установка налива ТИБА в танк контейнер 2. Реализация проекта ЦРП | K3: Успешное выполнение остановочного ремонта 2026 года | L3: Качественная | M3: Контракт | N3: ТНХ 2026 | O3: =INDEX('список ID из СУЭ с должностями'!$A:$F,MATCH(E3,'список ID из СУЭ с должностями'!$B:$B,0),5) -> 0
A4: 3 квартал 2026 | B4: Год + квартал | C4: 2026 | D4: 01.07.2026 - 30.09.2026 | E4: 1 | F4: Заместитель главного инженера | G4: Общество с ограниченной ответственностью "Томскнефтехим"/Направление Главного инженера/Направление заместителя главного инженера | H4: Базовые обязательства | I4: Подготовка и Выполнение остановочного ремонта согласно заявленным параметрам БП | J4: Подготовка и проведение ремонта по чек-листу не менее 95% | K4: Успешное выполнение остановочного ремонта 2026 года | L4: Качественная | M4: Контракт | N4: ТНХ 2026 | O4: =INDEX('список ID из СУЭ с должностями'!$A:$F,MATCH(E4,'список ID из СУЭ с должностями'!$B:$B,0),5) -> 0
A5: 3 квартал 2026 | B5: Год + квартал | C5: 2026 | D5: 01.07.2026 - 30.09.2026 | E5: 1 | F5: Заместитель главного инженера | G5: Общество с ограниченной ответственностью "Томскнефтехим"/Направление Главного инженера/Направление заместителя главного инженера | H5: Базовые обязательства | I5: Управление рабочим капиталом | J5: "Организация складского хранения: 1.нецелевые помещения освобождены и запломбированы 2.наведен порядок в целевых помещениях 3.установлен и соблюдается целевой процесс работы с МТР "" Соблюдение целевого уровня РК: Соблюдение общего уровня запасов РК на конец года в ЗО 3 121 млн.руб.: 1 373 млн.руб. СУОФ (МКЗ, МРП СУОФ, ЗИП) / 1 703 млн.руб СУН (АТЗ) / 45 млн.руб. МРП ИП Оборачиваемость МРП СУОФ текущего года поставки не более 90 дней Объем «срочных» заявок от общего годового объема не более 20% Подменный фонд к. 1027 разобран и поставлен на учет в систему до конца 3 кв. Избыточные запасы после проекта (Перевод в НВИ в течение 3 месяцев с даты закрытия проекта) - 0 руб." | K5: Выполнение ключевых финансово-экономических показателей | L5: Качественная | M5: Контракт | N5: ТНХ 2026 | O5: =INDEX('список ID из СУЭ с должностями'!$A:$F,MATCH(E5,'список ID из СУЭ с должностями'!$B:$B,0),5) -> 0
A6: 3 квартал 2026 | B6: Год + квартал | C6: 2026 | D6: 01.07.2026 - 30.09.2026 | E6: 1 | F6: Заместитель главного инженера | G6: Общество с ограниченной ответственностью "Томскнефтехим"/Направление Главного инженера/Направление заместителя главного инженера | H6: Базовые обязательства | I6: Исполнение/Не превышение бюджета ТОиР в рамках утвержденного БП | J6: не более 100 % | K6: Выполнение ключевых финансово-экономических показателей | L6: Количественная | M6: Контракт | N6: ТНХ 2026 | O6: =INDEX('список ID из СУЭ с должностями'!$A:$F,MATCH(E6,'список ID из СУЭ с должностями'!$B:$B,0),5) -> 0
A7: 3 квартал 2026 | B7: Год + квартал | C7: 2026 | D7: 01.07.2026 - 30.09.2026 | E7: 1 | F7: Заместитель главного инженера | G7: Общество с ограниченной ответственностью "Томскнефтехим"/Направление Главного инженера/Направление заместителя главного инженера | H7: Базовые обязательства | I7: Управление травматизмом | J7: "1. Полученные допуска по ГИ -100% 2. 0 событий в зоне ответственности с влиянием на Ltif предприятия 3. Кол-во ГОР и ОР в выходные дни не более 10% (отн. выход/будни) в среднем по предприятию. За исключением аварийных. | K7: Минимизация травматизма (LTIF) | L7: Качественная | M7: Контракт | N7: ТНХ 2026 | O7: =INDEX('список ID из СУЭ с должностями'!$A:$F,MATCH(E7,'список ID из СУЭ с должностями'!$B:$B,0),5) -> 0
A8: 3 квартал 2026 | B8: Год + квартал | C8: 2026 | D8: 01.07.2026 - 30.09.2026 | E8: 1 | F8: Заместитель главного инженера | G8: Общество с ограниченной ответственностью "Томскнефтехим"/Направление Главного инженера/Направление заместителя главного инженера | H8: Базовые обязательства | I8: Приживаемость метрик ПСС | J8: Ожидаемый результат не менее 90% Проведение внутренних аттестаций по результатам ЕКЭ РП и СУОФ (50% от общего объема) исполнение дорожной карты: Тираж Мини - Т Исполнение мероприятий проекта Сыгранность Мини-Т | K8: Обеспечить приживаемость Производственной системы | L8: Качественная | M8: Контракт | N8: ТНХ 2026 | O8: =INDEX('список ID из СУЭ с должностями'!$A:$F,MATCH(E8,'список ID из СУЭ с должностями'!$B:$B,0),5) -> 0
A9: 3 квартал 2026 | B9: Год + квартал | C9: 2026 | D9: 01.07.2026 - 30.09.2026 | E9: 2 | F9: Начальник смены производства | G9: Общество с ограниченной ответственностью "Томскнефтехим"/Направление Директора по производству/Производство полиэтилена/Смена 3 | H9: Долгосрочные цели | I9: Проведение Остановочного ремонта | J9: Организация проведения ОР (в ЗО): 1) в полном объеме 2) в установленный срок (согласно графика 4 уровня) 3) без нарушений требований безопасности (достаточность и полнота выполнения мероприятий по подготовке и проведению рабо) | K9: Успешное выполнение остановочного ремонта 2026 года | L9: Качественная | M9: Контракт | N9: ТНХ 2026 | O9: =INDEX('список ID из СУЭ с должностями'!$A:$F,MATCH(E9,'список ID из СУЭ с должностями'!$B:$B,0),5) -> НС
A10: 3 квартал 2026 | B10: Год + квартал | C10: 2026 | D10: 01.07.2026 - 30.09.2026 | E10: 2 | F10: Начальник смены производства | G10: Общество с ограниченной ответственностью "Томскнефтехим"/Направление Директора по производству/Производство полиэтилена/Смена 3 | H10: Базовые обязательства | I10: Выполнение целей стратегии устойчивого развития: | J10: 1. Выбросы ЗВ в атмосферу не более 0,225 2. Сбросы ЗВ в стоки не более 0,018 3. Отходы на размещение не более 0,050 4. Водопотребление, не более 21,7 5. Выбросы парниковых газов, не более 34,57 | K10: Выполнение целей стратегии устойчивого развития, % Не менее 100 % | L10: Качественная | M10: Контракт | N10: ТНХ 2026 | O10: =INDEX('список ID из СУЭ с должностями'!$A:$F,MATCH(E10,'список ID из СУЭ с должностями'!$B:$B,0),5) -> НС
A11: 3 квартал 2026 | B11: Год + квартал | C11: 2026 | D11: 01.07.2026 - 30.09.2026 | E11: 2 | F11: Начальник смены производства | G11: Общество с ограниченной ответственностью "Томскнефтехим"/Направление Директора по производству/Производство полиэтилена/Смена 3 | H11: Базовые обязательства | I11: Управление травматизмом (LTIF) и техногенностью ИА1,2 | J11: 1.Полученные допуски -99% (личные) 2. LTIF = 0 (ППЭ) 3. 0 пробитых барьеров при проведении стресс-тестов со стороны ОТ,ПБ (в ЗО смены) 4. ИА 1,2 = 0 | K11: Минимизация травматизма (LTIF) | L11: Качественная | M11: Контракт | N11: ТНХ 2026 | O11: =INDEX('список ID из СУЭ с должностями'!$A:$F,MATCH(E11,'список ID из СУЭ с должностями'!$B:$B,0),5) -> НС
A12: 3 квартал 2026 | B12: Год + квартал | C12: 2026 | D12: 01.07.2026 - 30.09.2026 | E12: 2 | F12: Начальник смены производства | G12: Общество с ограниченной ответственностью "Томскнефтехим"/Направление Директора по производству/Производство полиэтилена/Смена 3 | H12: Базовые обязательства | I12: HR Средний срок получения допуска к рабочему месту в ЗО не более 120 дней | J12: не более 120 дней | K12: Повышение производственной эффективности | L12: Количественная | M12: Контракт | N12: ТНХ 2026 | O12: =INDEX('список ID из СУЭ с должностями'!$A:$F,MATCH(E12,'список ID из СУЭ с должностями'!$B:$B,0),5) -> НС
A13: 3 квартал 2026 | B13: Год + квартал | C13: 2026 | D13: 01.07.2026 - 30.09.2026 | E13: 2 | F13: Начальник смены производства | G13: Общество с ограниченной ответственностью "Томскнефтехим"/Направление Директора по производству/Производство полиэтилена/Смена 3 | H13: Базовые обязательства | I13: Выполнение целей по качеству: - объем выпуска НСП | J13: КПОиТП не более 0,50 КЦП не менее 0,97 НСП более 5.97% | K13: Минимизация потерь | L13: Качественная | M13: Контракт | N13: ТНХ 2026 | O13: =INDEX('список ID из СУЭ с должностями'!$A:$F,MATCH(E13,'список ID из СУЭ с должностями'!$B:$B,0),5) -> НС
... A161: 3 квартал 2026 | B161: Год + квартал | C161: 2026 | D161: 01.07.2026 - 30.09.2026 | E161: 22 | F161: Специалист | G161: Общество с ограниченной ответственностью "Томскнефтехим"/Направление Директора по производству/Производство полиэтилена | H161: Задачи с эффектом в текущем году | I161: Соблюдение финансовой и исполнительной дисциплины | J161: График расчета заработной платы дневного персонала производства. | K161: Выполнение ключевых финансово-экономических показателей | L161: Качественная | M161: Контракт | N161: ТНХ 2026 | O161: =INDEX('список ID из СУЭ с должностями'!$A:$F,MATCH(E161,'список ID из СУЭ с должностями'!$B:$B,0),5) -> 0
A162: 3 квартал 2026 | B162: Год + квартал | C162: 2026 | D162: 01.07.2026 - 30.09.2026 | E162: 22 | F162: Специалист | G162: Общество с ограниченной ответственностью "Томскнефтехим"/Направление Директора по производству/Производство полиэтилена | H162: Долгосрочные цели | I162: Качество планирования | K162: Обеспечить приживаемость Производственной системы | L162: Качественная | M162: Контракт | N162: ТНХ 2026 | O162: =INDEX('список ID из СУЭ с должностями'!$A:$F,MATCH(E162,'список ID из СУЭ с должностями'!$B:$B,0),5) -> 0
A163: 3 квартал 2026 | B163: Год + квартал | C163: 2026 | D163: 01.07.2026 - 30.09.2026 | E163: 22 | F163: Специалист | G163: Общество с ограниченной ответственностью "Томскнефтехим"/Направление Директора по производству/Производство полиэтилена | H163: Базовые обязательства | I163: Качество ведения документооборота | J163: Своевременный пересмотр документации производства | K163: Обеспечить приживаемость Производственной системы | L163: Качественная | M163: Контракт | N163: ТНХ 2026 | O163: =INDEX('список ID из СУЭ с должностями'!$A:$F,MATCH(E163,'список ID из СУЭ с должностями'!$B:$B,0),5) -> 0
A164: 3 квартал 2026 | B164: Год + квартал | C164: 2026 | D164: 01.07.2026 - 30.09.2026 | E164: 23 | F164: Инженер по качеству испытаний | G164: Общество с ограниченной ответственностью "Томскнефтехим"/Служба главного технолога/Центральная заводская лаборатория | H164: Долгосрочные цели | I164: Применение ИИ в ЦЗЛ | J164: Генерация и реализация не менее 2-х процессов ЦЗЛ через ИИ | K164: Внедрение и обеспечение приживаемости инструментов ИИ | L164: Качественная | M164: Доп цели | N164: ТНХ 2026 | O164: =INDEX('список ID из СУЭ с должностями'!$A:$F,MATCH(E164,'список ID из СУЭ с должностями'!$B:$B,0),5) -> 0
A165: 3 квартал 2026 | B165: Год + квартал | C165: 2026 | D165: 01.07.2026 - 30.09.2026 | E165: 23 | F165: Инженер по качеству испытаний | G165: Общество с ограниченной ответственностью "Томскнефтехим"/Служба главного технолога/Центральная заводская лаборатория | H165: Базовые обязательства | I165: Подтверждение компетентности при аудите GMP | J165: Подготовка к аудиту, координация работ, отсутствие замечаний по процедурам ЦЗЛ | K165: Реализация производственного плана Не менее 426.1 тыс. тн | L165: Качественная | M165: Контракт | N165: ТНХ 2026 | O165: =INDEX('список ID из СУЭ с должностями'!$A:$F,MATCH(E165,'список ID из СУЭ с должностями'!$B:$B,0),5) -> 0
A166: 3 квартал 2026 | B166: Год + квартал | C166: 2026 | D166: 01.07.2026 - 30.09.2026 | E166: 23 | F166: Инженер по качеству испытаний | G166: Общество с ограниченной ответственностью "Томскнефтехим"/Служба главного технолога/Центральная заводская лаборатория | H166: Задачи с эффектом в текущем году | I166: Реализация программы развития ПСС | J166: Выполнение мероприятий по помещениям СЭК. Обучение в ЛК по СРР | K166: Обеспечить приживаемость Производственной системы | L166: Качественная | M166: Контракт | N166: ТНХ 2026 | O166: =INDEX('список ID из СУЭ с должностями'!$A:$F,MATCH(E166,'список ID из СУЭ с должностями'!$B:$B,0),5) -> 0
A167: 3 квартал 2026 | B167: Год + квартал | C167: 2026 | D167: 01.07.2026 - 30.09.2026 | E167: 23 | F167: Инженер по качеству испытаний | G167: Общество с ограниченной ответственностью "Томскнефтехим"/Служба главного технолога/Центральная заводская лаборатория | H167: Задачи с эффектом в текущем году | I167: Эффективное использование программы ЛИМС | J167: Организация работ по доработке Протокола испытаний в области аккредитации. Отсутствие замечаний по процедурам | K167: Реализация производственного плана Не менее 426.1 тыс. тн | L167: Качественная | M167: Контракт | N167: ТНХ 2026 | O167: =INDEX('список ID из СУЭ с должностями'!$A:$F,MATCH(E167,'список ID из СУЭ с должностями'!$B:$B,0),5) -> 0
A168: 3 квартал 2026 | B168: Год + квартал | C168: 2026 | D168: 01.07.2026 - 30.09.2026 | E168: 23 | F168: Инженер по качеству испытаний | G168: Общество с ограниченной ответственностью "Томскнефтехим"/Служба главного технолога/Центральная заводская лаборатория | H168: Задачи с эффектом в текущем году | I168: Развитие технических и функциональных компетенций персонала, в т.ч. по СМ | J168: Техническое обучение, проверка знаний, проработка кейсов по несоответствующим работам | K168: Реализация производственного плана Не менее 426.1 тыс. тн | L168: Качественная | M168: Контракт | N168: ТНХ 2026 | O168: =INDEX('список ID из СУЭ с должностями'!$A:$F,MATCH(E168,'список ID из СУЭ с должностями'!$B:$B,0),5) -> 0
A169: 3 квартал 2026 | B169: Год + квартал | C169: 2026 | D169: 01.07.2026 - 30.09.2026 | E169: 23 | F169: Инженер по качеству испытаний | G169: Общество с ограниченной ответственностью "Томскнефтехим"/Служба главного технолога/Центральная заводская лаборатория | H169: Базовые обязательства | I169: Развитие Системы менеджмента. Повышение результативности СМ | J169: 100% выполнение плана по повышению СМ | K169: Реализация производственного плана Не менее 426.1 тыс. тн | L169: Качественная | M169: Контракт | N169: ТНХ 2026 | O169: =INDEX('список ID из СУЭ с должностями'!$A:$F,MATCH(E169,'список ID из СУЭ с должностями'!$B:$B,0),5) -> 0
A170: 3 квартал 2026 | B170: Год + квартал | C170: 2026 | D170: 01.07.2026 - 30.09.2026 | E170: 23 | F170: Инженер по качеству испытаний | G170: Общество с ограниченной ответственностью "Томскнефтехим"/Служба главного технолога/Центральная заводская лаборатория | H170: Базовые обязательства | I170: Поддержание Культуры безопасности и экологичности в подразделении | J170: Вовлеченность сотрудников ЦЗЛ на уровне не ниже 100% - ЧБ, Экологии | K170: Минимизация травматизма (LTIF) | L170: Качественная | M170: Контракт | N170: ТНХ 2026 | O170: =INDEX('список ID из СУЭ с должностями'!$A:$F,MATCH(E170,'список ID из СУЭ с должностями'!$B:$B,0),5) -> 0
A171: 3 квартал 2026 | B171: Год + квартал | C171: 2026 | D171: 01.07.2026 - 30.09.2026 | E171: 23 | F171: Инженер по качеству испытаний | G171: Общество с ограниченной ответственностью "Томскнефтехим"/Служба главного технолога/Центральная заводская лаборатория | H171: Задачи с эффектом в текущем году | I171: Автоматизация результатов измерений аутсорсинговой лабораторий | J171: Результаты вносятся КА в систему ЛИМС, производство оперативно получает результат измерений | K171: Выполнение целей стратегии устойчивого развития, % Не менее 100 % | L171: Качественная | M171: Контракт | N171: ТНХ 2026 | O171: =INDEX('список ID из СУЭ с должностями'!$A:$F,MATCH(E171,'список ID из СУЭ с должностями'!$B:$B,0),5) -> 0
A172: 3 квартал 2026 | B172: Год + квартал | C172: 2026 | D172: 01.07.2026 - 30.09.2026 | E172: 23 | F172: Инженер по качеству испытаний | G172: Общество с ограниченной ответственностью "Томскнефтехим"/Служба главного технолога/Центральная заводская лаборатория | H172: Базовые обязательства | I172: Успешное проведение ОР 2026 в зоне ответственности | J172: 100% выполнение ГАК в зоне ответственности, организация оперативной доставки проб и выдачи результатов | K172: Успешное выполнение остановочного ремонта 2026 года | L172: Качественная | M172: Контракт | N172: ТНХ 2026 | O172: =INDEX('список ID из СУЭ с должностями'!$A:$F,MATCH(E172,'список ID из СУЭ с должностями'!$B:$B,0),5) -> 0
A173: 3 квартал 2026 | B173: Год + квартал | C173: 2026 | D173: 01.07.2026 - 30.09.2026 | E173: 23 | F173: Инженер по качеству испытаний | G173: Общество с ограниченной ответственностью "Томскнефтехим"/Служба главного технолога/Центральная заводская лаборатория | H173: Задачи с эффектом в текущем году | I173: Проект ТИБА- организация выполнение добавленного объема текущим ресурсом | J173: Сформирован ГАК на период пуска и стабильной работы с учетом рисков по качеству и трудозатратам ЦЗЛ | K173: Повышение производственной эффективности | L173: Качественная | M173: Контракт | N173: ТНХ 2026 | O173: =INDEX('список ID из СУЭ с должностями'!$A:$F,MATCH(E173,'список ID из СУЭ с должностями'!$B:$B,0),5) -> 0
A174: 3 квартал 2026 | B174: Год + квартал | C174: 2026 | D174: 01.07.2026 - 30.09.2026 | E174: 24 | F174: Инженер по автоматизации | G174: Общество с ограниченной ответственностью "Томскнефтехим"/Направление Главного инженера/Направление заместителя главного инженера/Служба управления основными фондами/Отдел технического обслуживания и ремонтов/Техническое обслуживание и ремонты Производства полипропилена | H174: Базовые обязательства | I174: Управление ремонтом -Автоматизация ПП | J174: Внесение в БДО новых ЕО, в рамках реализации проекта АСУТП и ЛСУ экструдера Р2.2 | K174: Повышение производственной эффективности | L174: Качественная | M174: Контракт | N174: ТНХ 2026 | O174: =INDEX('список ID из СУЭ с должностями'!$A:$F,MATCH(E174,'список ID из СУЭ с должностями'!$B:$B,0),5) -> 0
... A288: 3 квартал 2026 | B288: Год + квартал | C288: 2026 | D288: 01.07.2026 - 30.09.2026 | E288: 38 | F288: Старший химик | G288: Общество с ограниченной ответственностью "Томскнефтехим"/Служба главного технолога/Центральная заводская лаборатория/Смена 1 | H288: Долгосрочные цели | I288: Развитие системы менеджмента в смене | J288: Знание и соблюдение РК сотрудников смены. Линеаризация и обеспечение приживаемости вводимых процессов в смене | K288: Повышение производственной эффективности | L288: Качественная | M288: Контракт | N288: ТНХ 2026 | O288: =INDEX('список ID из СУЭ с должностями'!$A:$F,MATCH(E288,'список ID из СУЭ с должностями'!$B:$B,0),5) -> 0
A289: 3 квартал 2026 | B289: Год + квартал | C289: 2026 | D289: 01.07.2026 - 30.09.2026 | E289: 39 | F289: Эксперт | G289: Общество с ограниченной ответственностью "Томскнефтехим"/Направление Главного инженера/Служба управления надежностью/Лаборатория неразрушающего контроля и диагностики | H289: Базовые обязательства | I289: Минимизация травматизма (LTIF) | J289: 0 | K289: Минимизация травматизма (LTIF) | L289: Качественная | M289: Контракт | N289: ТНХ 2026 | O289: =INDEX('список ID из СУЭ с должностями'!$A:$F,MATCH(E289,'список ID из СУЭ с должностями'!$B:$B,0),5) -> 0
A290: 3 квартал 2026 | B290: Год + квартал | C290: 2026 | D290: 01.07.2026 - 30.09.2026 | E290: 39 | F290: Эксперт | G290: Общество с ограниченной ответственностью "Томскнефтехим"/Направление Главного инженера/Служба управления надежностью/Лаборатория неразрушающего контроля и диагностики | H290: Базовые обязательства | I290: Минимизация аварийности производственных объектов (ИА1) | J290: 0 | K290: Минимизация аварийности производственных объектов (ИА1) | L290: Качественная | M290: Контракт | N290: ТНХ 2026 | O290: =INDEX('список ID из СУЭ с должностями'!$A:$F,MATCH(E290,'список ID из СУЭ с должностями'!$B:$B,0),5) -> 0
A291: 3 квартал 2026 | B291: Год + квартал | C291: 2026 | D291: 01.07.2026 - 30.09.2026 | E291: 39 | F291: Эксперт | G291: Общество с ограниченной ответственностью "Томскнефтехим"/Направление Главного инженера/Служба управления надежностью/Лаборатория неразрушающего контроля и диагностики | H291: Задачи с эффектом в текущем году | I291: Успешное выполнение работ в период ОР-26 | J291: Работы выполнены безопасно и в срок. | K291: Успешное выполнение остановочного ремонта 2026 года | L291: Качественная | M291: Контракт | N291: ТНХ 2026 | O291: =INDEX('список ID из СУЭ с должностями'!$A:$F,MATCH(E291,'список ID из СУЭ с должностями'!$B:$B,0),5) -> 0
A292: 3 квартал 2026 | B292: Год + квартал | C292: 2026 | D292: 01.07.2026 - 30.09.2026 | E292: 39 | F292: Эксперт | G292: Общество с ограниченной ответственностью "Томскнефтехим"/Направление Главного инженера/Служба управления надежностью/Лаборатория неразрушающего контроля и диагностики | H292: Задачи с эффектом в текущем году | I292: Проведение СЭЗ и подтверждение лицензируемых требований для ИИИ | J292: Проведение независимой экспертизы с целью замены СЭЗ и регистрацией нового рентген аппарата, а так же подтверждение выполнения требований для лицензиата применяющий источники ионизирующего излучения. | K292: Выполнение целей стратегии устойчивого развития, % Не менее 100 % | L292: Качественная | M292: Контракт | N292: ТНХ 2026 | O292: =INDEX('список ID из СУЭ с должностями'!$A:$F,MATCH(E292,'список ID из СУЭ с должностями'!$B:$B,0),5) -> 0
A293: 3 квартал 2026 | B293: Год + квартал | C293: 2026 | D293: 01.07.2026 - 30.09.2026 | E293: 39 | F293: Эксперт | G293: Общество с ограниченной ответственностью "Томскнефтехим"/Направление Главного инженера/Служба управления надежностью/Лаборатория неразрушающего контроля и диагностики | H293: Задачи с эффектом в текущем году | I293: Приживаемость Производственной системы | J293: не менее 90 % | K293: Обеспечить приживаемость Производственной системы | L293: Количественная | M293: Контракт | N293: ТНХ 2026 | O293: =INDEX('список ID из СУЭ с должностями'!$A:$F,MATCH(E293,'список ID из СУЭ с должностями'!$B:$B,0),5) -> 0
A294: 3 квартал 2026 | B294: Год + квартал | C294: 2026 | D294: 01.07.2026 - 30.09.2026 | E294: 40 | F294: Специалист | G294: Общество с ограниченной ответственностью "Томскнефтехим"/Направление Главного инженера/Направление заместителя главного инженера/Управление материально-техническим обеспечением производства/Складское хозяйство | H294: Базовые обязательства | I294: Реализация УМШ | J294: не менее 1 Шт | K294: Повышение эффективности внутренних процессов функции | L294: Количественная | M294: Контракт | N294: ФОП 2026 | O294: =INDEX('список ID из СУЭ с должностями'!$A:$F,MATCH(E294,'список ID из СУЭ с должностями'!$B:$B,0),5) -> 0
A295: 3 квартал 2026 | B295: Год + квартал | C295: 2026 | D295: 01.07.2026 - 30.09.2026 | E295: 40 | F295: Специалист | G295: Общество с ограниченной ответственностью "Томскнефтехим"/Направление Главного инженера/Направление заместителя главного инженера/Управление материально-техническим обеспечением производства/Складское хозяйство | H295: Базовые обязательства | I295: Ознакомление с документами в системе КИС ЕСМ | J295: не менее 100 % | K295: Выполнение целей стратегии устойчивого развития, % Не менее 100 % | L295: Количественная | M295: Контракт | N295: ТНХ 2026 | O295: =INDEX('список ID из СУЭ с должностями'!$A:$F,MATCH(E295,'список ID из СУЭ с должностями'!$B:$B,0),5) -> 0
A296: 3 квартал 2026 | B296: Год + квартал | C296: 2026 | D296: 01.07.2026 - 30.09.2026 | E296: 40 | F296: Специалист | G296: Общество с ограниченной ответственностью "Томскнефтехим"/Направление Главного инженера/Направление заместителя главного инженера/Управление материально-техническим обеспечением производства/Складское хозяйство | H296: Базовые обязательства | I296: соблюдению чистоты в складе | J296: не менее 6 шт | K296: Повышение производственной эффективности | L296: Количественная | M296: Контракт | N296: ТНХ 2026 | O296: =INDEX('список ID из СУЭ с должностями'!$A:$F,MATCH(E296,'список ID из СУЭ с должностями'!$B:$B,0),5) -> 0
A297: 3 квартал 2026 | B297: Год + квартал | C297: 2026 | D297: 01.07.2026 - 30.09.2026 | E297: 40 | F297: Специалист | G297: Общество с ограниченной ответственностью "Томскнефтехим"/Направление Главного инженера/Направление заместителя главного инженера/Управление материально-техническим обеспечением производства/Складское хозяйство | H297: Задачи с эффектом в текущем году | I297: Проведение поведенческих аудитов (ПАБ) с выявлением ОУ и ОД, шт. | J297: не менее 3 шт | K297: Выполнение целей стратегии устойчивого развития, % Не менее 100 % | L297: Количественная | M297: Контракт | N297: ТНХ 2026 | O297: =INDEX('список ID из СУЭ с должностями'!$A:$F,MATCH(E297,'список ID из СУЭ с должностями'!$B:$B,0),5) -> 0
A298: 3 квартал 2026 | B298: Год + квартал | C298: 2026 | D298: 01.07.2026 - 30.09.2026 | E298: 40 | F298: Специалист | G298: Общество с ограниченной ответственностью "Томскнефтехим"/Направление Главного инженера/Направление заместителя главного инженера/Управление материально-техническим обеспечением производства/Складское хозяйство | H298: Базовые обязательства | I298: Наличие ШК и скан-копий в мониторе ФПД | J298: не менее 100 % | K298: Повышение производственной эффективности | L298: Количественная | M298: Контракт | N298: ТНХ 2026 | O298: =INDEX('список ID из СУЭ с должностями'!$A:$F,MATCH(E298,'список ID из СУЭ с должностями'!$B:$B,0),5) -> 0
A299: 3 квартал 2026 | B299: Год + квартал | C299: 2026 | D299: 01.07.2026 - 30.09.2026 | E299: 40 | F299: Специалист | G299: Общество с ограниченной ответственностью "Томскнефтехим"/Направление Главного инженера/Направление заместителя главного инженера/Управление материально-техническим обеспечением производства/Складское хозяйство | H299: Задачи с эффектом в текущем году | I299: Контроль несогласованного списания МТР с ЦС | J299: Списанные с ЦС МТР выданы заказчику или проведено сторно списанния | K299: Минимизация потерь | L299: Качественная | M299: Контракт | N299: ТНХ 2026 | O299: =INDEX('список ID из СУЭ с должностями'!$A:$F,MATCH(E299,'список ID из СУЭ с должностями'!$B:$B,0),5) -> 0
A300: 3 квартал 2026 | B300: Год + квартал | C300: 2026 | D300: 01.07.2026 - 30.09.2026 | E300: 40 | F300: Специалист | G300: Общество с ограниченной ответственностью "Томскнефтехим"/Направление Главного инженера/Направление заместителя главного инженера/Управление материально-техническим обеспечением производства/Складское хозяйство | H300: Базовые обязательства | I300: Контроль внесения конечного срока хранения МТР в признаки партии | J300: не менее 100 % | K300: Повышение эффективности внутренних процессов функции | L300: Количественная | M300: Контракт | N300: ФОП 2026 | O300: =INDEX('список ID из СУЭ с должностями'!$A:$F,MATCH(E300,'список ID из СУЭ с должностями'!$B:$B,0),5) -> 0
A301: 3 квартал 2026 | B301: Год + квартал | C301: 2026 | D301: 01.07.2026 - 30.09.2026 | E301: 40 | F301: Специалист | G301: Общество с ограниченной ответственностью "Томскнефтехим"/Направление Главного инженера/Направление заместителя главного инженера/Управление материально-техническим обеспечением производства/Складское хозяйство | H301: Базовые обязательства | I301: Контроль ведения журналов регистрации в сетевых ресурсах | J301: Акты ведутся должным образом (все обязательные поля заполнены, приложения сохранены с соответствующих папках ) | K301: Повышение эффективности внутренних процессов функции | L301: Качественная | M301: Контракт | N301: ФОП 2026 | O301: =INDEX('список ID из СУЭ с должностями'!$A:$F,MATCH(E301,'список ID из СУЭ с должностями'!$B:$B,0),5) -> 0
A302: 3 квартал 2026 | B302: Год + квартал | C302: 2026 | D302: 01.07.2026 - 30.09.2026 | E302: 40 | F302: Специалист | G302: Общество с ограниченной ответственностью "Томскнефтехим"/Направление Главного инженера/Направление заместителя главного инженера/Управление материально-техническим обеспечением производства/Складское хозяйство | H302: Базовые обязательства | I302: Внесение складских мест хранения МТР | J302: не менее 100 % | K302: Повышение эффективности внутренних процессов функции | L302: Количественная | M302: Контракт | N302: ФОП 2026 | O302: =INDEX('список ID из СУЭ с должностями'!$A:$F,MATCH(E302,'список ID из СУЭ с должностями'!$B:$B,0),5) -> 0
... A373: 3 квартал 2026 | B373: Год + квартал | C373: 2026 | D373: 01.07.2026 - 30.09.2026 | E373: 50 | F373: Инженер | G373: Общество с ограниченной ответственностью "Томскнефтехим"/Направление Директора по производству/Производство мономеров/Смена 1/Установка пиролиза углеводородов нефти | H373: Базовые обязательства | I373: Снижение нарушений НТР | J373: не более 1665 шт | K373: Повышение производственной эффективности | L373: Количественная | M373: Контракт | N373: ТНХ 2026 | O373: =INDEX('список ID из СУЭ с должностями'!$A:$F,MATCH(E373,'список ID из СУЭ с должностями'!$B:$B,0),5) -> Инж смены
A374: 3 квартал 2026 | B374: Год + квартал | C374: 2026 | D374: 01.07.2026 - 30.09.2026 | E374: 51 | F374: Ведущий инженер по исследованию металлов | G374: Общество с ограниченной ответственностью "Томскнефтехим"/Направление Главного инженера/Служба управления надежностью/Лаборатория неразрушающего контроля и диагностики | H374: Базовые обязательства | I374: Минимизация травматизма (LTIF) | J374: 0 | K374: Минимизация травматизма (LTIF) | L374: Качественная | M374: Контракт | N374: ТНХ 2026 | O374: =INDEX('список ID из СУЭ с должностями'!$A:$F,MATCH(E374,'список ID из СУЭ с должностями'!$B:$B,0),5) -> 0
A375: 3 квартал 2026 | B375: Год + квартал | C375: 2026 | D375: 01.07.2026 - 30.09.2026 | E375: 51 | F375: Ведущий инженер по исследованию металлов | G375: Общество с ограниченной ответственностью "Томскнефтехим"/Направление Главного инженера/Служба управления надежностью/Лаборатория неразрушающего контроля и диагностики | H375: Базовые обязательства | I375: Минимизация аварийности производственных объектов (ИА1) | J375: 0 | K375: Минимизация аварийности производственных объектов (ИА1) | L375: Качественная | M375: Контракт | N375: ТНХ 2026 | O375: =INDEX('список ID из СУЭ с должностями'!$A:$F,MATCH(E375,'список ID из СУЭ с должностями'!$B:$B,0),5) -> 0
A376: 3 квартал 2026 | B376: Год + квартал | C376: 2026 | D376: 01.07.2026 - 30.09.2026 | E376: 51 | F376: Ведущий инженер по исследованию металлов | G376: Общество с ограниченной ответственностью "Томскнефтехим"/Направление Главного инженера/Служба управления надежностью/Лаборатория неразрушающего контроля и диагностики | H376: Задачи с эффектом в текущем году | I376: Успешное выполнение работ в период ОР-26 | J376: Работы выполнены безопасно и в срок. | K376: Успешное выполнение остановочного ремонта 2026 года | L376: Качественная | M376: Контракт | N376: ТНХ 2026 | O376: =INDEX('список ID из СУЭ с должностями'!$A:$F,MATCH(E376,'список ID из СУЭ с должностями'!$B:$B,0),5) -> 0
A377: 3 квартал 2026 | B377: Год + квартал | C377: 2026 | D377: 01.07.2026 - 30.09.2026 | E377: 51 | F377: Ведущий инженер по исследованию металлов | G377: Общество с ограниченной ответственностью "Томскнефтехим"/Направление Главного инженера/Служба управления надежностью/Лаборатория неразрушающего контроля и диагностики | H377: Долгосрочные цели | I377: Профессиональное развитие сотрудника. | J377: Обучение сотрудника практическим навыкам металлографического анализа, механических испытаний. Изучение методов, оборудования, НД. Сотрудник после обучения качественно проводит испытания с выдачей заключения. | K377: Выполнение целей стратегии устойчивого развития, % Не менее 100 % | L377: Качественная | M377: Контракт | N377: ТНХ 2026 | O377: =INDEX('список ID из СУЭ с должностями'!$A:$F,MATCH(E377,'список ID из СУЭ с должностями'!$B:$B,0),5) -> 0
A378: 3 квартал 2026 | B378: Год + квартал | C378: 2026 | D378: 01.07.2026 - 30.09.2026 | E378: 51 | F378: Ведущий инженер по исследованию металлов | G378: Общество с ограниченной ответственностью "Томскнефтехим"/Направление Главного инженера/Служба управления надежностью/Лаборатория неразрушающего контроля и диагностики | H378: Задачи с эффектом в текущем году | I378: Приживаемость Производственной системы | J378: не менее 90 % | K378: Обеспечить приживаемость Производственной системы | L378: Количественная | M378: Контракт | N378: ТНХ 2026 | O378: =INDEX('список ID из СУЭ с должностями'!$A:$F,MATCH(E378,'список ID из СУЭ с должностями'!$B:$B,0),5) -> 0
A379: 3 квартал 2026 | B379: Год + квартал | C379: 2026 | D379: 01.07.2026 - 30.09.2026 | E379: 51 | F379: Ведущий инженер по исследованию металлов | G379: Общество с ограниченной ответственностью "Томскнефтехим"/Направление Главного инженера/Служба управления надежностью/Лаборатория неразрушающего контроля и диагностики | H379: Задачи с эффектом в текущем году | I379: Управление травматизмом (LTIF) в зоне ответственности | J379: LTIF = 0 | K379: Минимизация травматизма (LTIF) | L379: Качественная | M379: Контракт | N379: ТНХ 2026 | O379: =INDEX('список ID из СУЭ с должностями'!$A:$F,MATCH(E379,'список ID из СУЭ с должностями'!$B:$B,0),5) -> 0
A380: 3 квартал 2026 | B380: Год + квартал | C380: 2026 | D380: 01.07.2026 - 30.09.2026 | E380: 51 | F380: Ведущий инженер по исследованию металлов | G380: Общество с ограниченной ответственностью "Томскнефтехим"/Направление Главного инженера/Служба управления надежностью/Лаборатория неразрушающего контроля и диагностики | H380: Долгосрочные цели | I380: Профессиональное развитие сотрудника. | J380: Обучение сотрудника навыкам спектрального анализа на рабочем месте. Изучение метода, оборудования, НД. Сотрудник после обучения правильно проводит контроль металла, корректно выдано заключение. | K380: Выполнение целей стратегии устойчивого развития, % Не менее 100 % | L380: Качественная | M380: Контракт | N380: ТНХ 2026 | O380: =INDEX('список ID из СУЭ с должностями'!$A:$F,MATCH(E380,'список ID из СУЭ с должностями'!$B:$B,0),5) -> 0
A381: 3 квартал 2026 | B381: Год + квартал | C381: 2026 | D381: 01.07.2026 - 30.09.2026 | E381: 51 | F381: Ведущий инженер по исследованию металлов | G381: Общество с ограниченной ответственностью "Томскнефтехим"/Направление Главного инженера/Служба управления надежностью/Лаборатория неразрушающего контроля и диагностики | H381: Задачи с эффектом в текущем году | I381: Индекс аварийности | J381: не более 0 событие | K381: Минимизация аварийности производственных объектов (ИА1) | L381: Количественная | M381: Контракт | N381: ТНХ 2026 | O381: =INDEX('список ID из СУЭ с должностями'!$A:$F,MATCH(E381,'список ID из СУЭ с должностями'!$B:$B,0),5) -> 0
A382: 3 квартал 2026 | B382: Год + квартал | C382: 2026 | D382: 01.07.2026 - 30.09.2026 | E382: 51 | F382: Ведущий инженер по исследованию металлов | G382: Общество с ограниченной ответственностью "Томскнефтехим"/Направление Главного инженера/Служба управления надежностью/Лаборатория неразрушающего контроля и диагностики | H382: Задачи с эффектом в текущем году | I382: Делопроизводство | J382: Организация и обработка документов, обеспечивающих правильное функционирование лаборатории | K382: Выполнение целей стратегии устойчивого развития, % Не менее 100 % | L382: Качественная | M382: Контракт | N382: ТНХ 2026 | O382: =INDEX('список ID из СУЭ с должностями'!$A:$F,MATCH(E382,'список ID из СУЭ с должностями'!$B:$B,0),5) -> 0
A383: 3 квартал 2026 | B383: Год + квартал | C383: 2026 | D383: 01.07.2026 - 30.09.2026 | E383: 52 | F383: Химик | G383: Общество с ограниченной ответственностью "Томскнефтехим"/Служба главного технолога/Центральная заводская лаборатория/Смена 1 | H383: Базовые обязательства | I383: Реализация программы развития ПСС в ЦЗЛ на 2026г. | J383: Выполнение плана работ по ПСС в препараторской за 3 кв 2026 г. | K383: Обеспечить приживаемость Производственной системы | L383: Качественная | M383: Контракт | N383: ТНХ 2026 | O383: =INDEX('список ID из СУЭ с должностями'!$A:$F,MATCH(E383,'список ID из СУЭ с должностями'!$B:$B,0),5) -> 0
A384: 3 квартал 2026 | B384: Год + квартал | C384: 2026 | D384: 01.07.2026 - 30.09.2026 | E384: 52 | F384: Химик | G384: Общество с ограниченной ответственностью "Томскнефтехим"/Служба главного технолога/Центральная заводская лаборатория/Смена 1 | H384: Задачи с эффектом в текущем году | I384: Рациональное использование ресурсов ЦЗЛ | J384: Реактивы, материалы, посуда, оборудование используются по действующим методикам и правилам ЦЗЛ, вносятся предложения по улучшениям процессов | K384: Выполнение ключевых финансово-экономических показателей | L384: Качественная | M384: Контракт | N384: ТНХ 2026 | O384: =INDEX('список ID из СУЭ с должностями'!$A:$F,MATCH(E384,'список ID из СУЭ с должностями'!$B:$B,0),5) -> 0
A385: 3 квартал 2026 | B385: Год + квартал | C385: 2026 | D385: 01.07.2026 - 30.09.2026 | E385: 52 | F385: Химик | G385: Общество с ограниченной ответственностью "Томскнефтехим"/Служба главного технолога/Центральная заводская лаборатория/Смена 1 | H385: Базовые обязательства | I385: Развитие функциональных компетенций | J385: Прохождение обучения, получение допусков на вновь вводимом оборудовании. Обучение в рамках программ СИБУРИНТЕХ. | K385: Выполнение целей стратегии устойчивого развития, % Не менее 100 % | L385: Качественная | M385: Контракт | N385: ТНХ 2026 | O385: =INDEX('список ID из СУЭ с должностями'!$A:$F,MATCH(E385,'список ID из СУЭ с должностями'!$B:$B,0),5) -> 0
A386: 3 квартал 2026 | B386: Год + квартал | C386: 2026 | D386: 01.07.2026 - 30.09.2026 | E386: 52 | F386: Химик | G386: Общество с ограниченной ответственностью "Томскнефтехим"/Служба главного технолога/Центральная заводская лаборатория/Смена 1 | H386: Базовые обязательства | I386: Развитие технических компетенций | J386: Выполнение плана работы УОТ на 3 кв.2026г. | K386: Реализация производственного плана Не менее 426.1 тыс. тн | L386: Качественная | M386: Контракт | N386: ТНХ 2026 | O386: =INDEX('список ID из СУЭ с должностями'!$A:$F,MATCH(E386,'список ID из СУЭ с должностями'!$B:$B,0),5) -> 0
A387: 3 квартал 2026 | B387: Год + квартал | C387: 2026 | D387: 01.07.2026 - 30.09.2026 | E387: 52 | F387: Химик | G387: Общество с ограниченной ответственностью "Томскнефтехим"/Служба главного технолога/Центральная заводская лаборатория/Смена 1 | H387: Долгосрочные цели | I387: Развитие системы менеджмента | J387: Знать и соблюдать РК ЦЗЛ. Отсутствие замечаний по процедурам, действующим в ЦЗЛ. | K387: Реализация производственного плана Не менее 426.1 тыс. тн | L387: Качественная | M387: Контракт | N387: ТНХ 2026 | O387: =INDEX('список ID из СУЭ с должностями'!$A:$F,MATCH(E387,'список ID из СУЭ с должностями'!$B:$B,0),5) -> 0
... A414: 3 квартал 2026 | B414: Год + квартал | C414: 2026 | D414: 01.07.2026 - 30.09.2026 | E414: 55 | F414: Инженер | G414: Общество с ограниченной ответственностью "Томскнефтехим"/Направление Директора по производству/Производство мономеров/Смена 2/Установка пиролиза углеводородов нефти | H414: Базовые обязательства | I414: Количество пультовых операций в зоне ответственности | J414: не более 30600 шт | K414: Повышение производственной эффективности | L414: Количественная | M414: Контракт | N414: ТНХ 2026 | O414: =INDEX('список ID из СУЭ с должностями'!$A:$F,MATCH(E414,'список ID из СУЭ с должностями'!$B:$B,0),5) -> Инж смены
A415: 3 квартал 2026 | B415: Год + квартал | C415: 2026 | D415: 01.07.2026 - 30.09.2026 | E415: 56 | F415: Инженер по вибродиагностике | G415: Общество с ограниченной ответственностью "Томскнефтехим"/Направление Главного инженера/Служба управления надежностью/Лаборатория неразрушающего контроля и диагностики | H415: Базовые обязательства | I415: Минимизация травматизма (LTIF) | J415: 0 | K415: Минимизация травматизма (LTIF) | L415: Качественная | M415: Контракт | N415: ТНХ 2026 | O415: =INDEX('список ID из СУЭ с должностями'!$A:$F,MATCH(E415,'список ID из СУЭ с должностями'!$B:$B,0),5) -> 0
A416: 3 квартал 2026 | B416: Год + квартал | C416: 2026 | D416: 01.07.2026 - 30.09.2026 | E416: 56 | F416: Инженер по вибродиагностике | G416: Общество с ограниченной ответственностью "Томскнефтехим"/Направление Главного инженера/Служба управления надежностью/Лаборатория неразрушающего контроля и диагностики | H416: Базовые обязательства | I416: Минимизация аварийности производственных объектов (ИА1) | J416: 0 | K416: Минимизация аварийности производственных объектов (ИА1) | L416: Качественная | M416: Контракт | N416: ТНХ 2026 | O416: =INDEX('список ID из СУЭ с должностями'!$A:$F,MATCH(E416,'список ID из СУЭ с должностями'!$B:$B,0),5) -> 0
A417: 3 квартал 2026 | B417: Год + квартал | C417: 2026 | D417: 01.07.2026 - 30.09.2026 | E417: 56 | F417: Инженер по вибродиагностике | G417: Общество с ограниченной ответственностью "Томскнефтехим"/Направление Главного инженера/Служба управления надежностью/Лаборатория неразрушающего контроля и диагностики | H417: Задачи с эффектом в текущем году | I417: Успешное выполнение работ в период ОР-26 | J417: Работы выполнены безопасно и в срок. | K417: Успешное выполнение остановочного ремонта 2026 года | L417: Качественная | M417: Контракт | N417: ТНХ 2026 | O417: =INDEX('список ID из СУЭ с должностями'!$A:$F,MATCH(E417,'список ID из СУЭ с должностями'!$B:$B,0),5) -> 0
A418: 3 квартал 2026 | B418: Год + квартал | C418: 2026 | D418: 01.07.2026 - 30.09.2026 | E418: 56 | F418: Инженер по вибродиагностике | G418: Общество с ограниченной ответственностью "Томскнефтехим"/Направление Главного инженера/Служба управления надежностью/Лаборатория неразрушающего контроля и диагностики | H418: Базовые обязательства | I418: Пройти дистанционное обучение, предлагаемое порталом Сибур | J418: не менее 1 шт | K418: Повышение производственной эффективности | L418: Количественная | M418: Контракт | N418: ТНХ 2026 | O418: =INDEX('список ID из СУЭ с должностями'!$A:$F,MATCH(E418,'список ID из СУЭ с должностями'!$B:$B,0),5) -> 0
A419: 3 квартал 2026 | B419: Год + квартал | C419: 2026 | D419: 01.07.2026 - 30.09.2026 | E419: 56 | F419: Инженер по вибродиагностике | G419: Общество с ограниченной ответственностью "Томскнефтехим"/Направление Главного инженера/Служба управления надежностью/Лаборатория неразрушающего контроля и диагностики | H419: Задачи с эффектом в текущем году | I419: Консультирование коллег по методу РК | J419: Проводить консультирование и экспертную помощь по вопросам классификации выявленных дефектов при расшифровке рентгеновских снимков. | K419: Повышение производственной эффективности | L419: Качественная | M419: Контракт | N419: ТНХ 2026 | O419: =INDEX('список ID из СУЭ с должностями'!$A:$F,MATCH(E419,'список ID из СУЭ с должностями'!$B:$B,0),5) -> 0
A420: 3 квартал 2026 | B420: Год + квартал | C420: 2026 | D420: 01.07.2026 - 30.09.2026 | E420: 56 | F420: Инженер по вибродиагностике | G420: Общество с ограниченной ответственностью "Томскнефтехим"/Направление Главного инженера/Служба управления надежностью/Лаборатория неразрушающего контроля и диагностики | H420: Базовые обязательства | I420: Изучение теоретического материала | J420: Изучить материалы по книге А.Б. Колобова. «Вибромониторинг промышленных машин» глава №3. | K420: Повышение производственной эффективности | L420: Качественная | M420: Контракт | N420: ТНХ 2026 | O420: =INDEX('список ID из СУЭ с должностями'!$A:$F,MATCH(E420,'список ID из СУЭ с должностями'!$B:$B,0),5) -> 0
A421: 3 квартал 2026 | B421: Год + квартал | C421: 2026 | D421: 01.07.2026 - 30.09.2026 | E421: 56 | F421: Инженер по вибродиагностике | G421: Общество с ограниченной ответственностью "Томскнефтехим"/Направление Главного инженера/Служба управления надежностью/Лаборатория неразрушающего контроля и диагностики | H421: Базовые обязательства | I421: Наращивание практического опыта | J421: Наращивание практического опыта по ВД НК (снятие фазы, снятие спектров в различных частотных диапазонах), анализ и проведение оценочных мероприятий. | K421: Повышение производственной эффективности | L421: Качественная | M421: Контракт | N421: ТНХ 2026 | O421: =INDEX('список ID из СУЭ с должностями'!$A:$F,MATCH(E421,'список ID из СУЭ с должностями'!$B:$B,0),5) -> 0
A422: 3 квартал 2026 | B422: Год + квартал | C422: 2026 | D422: 01.07.2026 - 30.09.2026 | E422: 57 | F422: Инженер | G422: Общество с ограниченной ответственностью "Томскнефтехим"/Направление Директора по производству/Производство мономеров/Смена 4 | H422: Базовые обязательства | I422: ЦНД | J422: Доля НД непрошедших проверки РПО из-за критических замечаний по отношению к общему количеству подготовленных исполнителем НД не более 10%. | K422: - | L422: Качественная | M422: Прочее | N422: Кросс-функциональные задачи | O422: =INDEX('список ID из СУЭ с должностями'!$A:$F,MATCH(E422,'список ID из СУЭ с должностями'!$B:$B,0),5) -> Инж смены
A423: 3 квартал 2026 | B423: Год + квартал | C423: 2026 | D423: 01.07.2026 - 30.09.2026 | E423: 57 | F423: Инженер | G423: Общество с ограниченной ответственностью "Томскнефтехим"/Направление Директора по производству/Производство мономеров/Смена 4 | H423: Базовые обязательства | I423: Управление травматизмом (LTIF) и техногенностью ИА1,2 | J423: LTIF = 0, ИА 1,2=0 | K423: Минимизация травматизма (LTIF) | L423: Качественная | M423: Контракт | N423: ТНХ 2026 | O423: =INDEX('список ID из СУЭ с должностями'!$A:$F,MATCH(E423,'список ID из СУЭ с должностями'!$B:$B,0),5) -> Инж смены
A424: 3 квартал 2026 | B424: Год + квартал | C424: 2026 | D424: 01.07.2026 - 30.09.2026 | E424: 57 | F424: Инженер | G424: Общество с ограниченной ответственностью "Томскнефтехим"/Направление Директора по производству/Производство мономеров/Смена 4 | H424: Базовые обязательства | I424: Снижение количества срабатывания сигнализаций, нарушений НТР | J424: сигнализации - 16500 шт. НТР - не более 1665 шт./кв. НАК - не более 558 шт./кв. | K424: Повышение производственной эффективности | L424: Качественная | M424: Контракт | N424: ТНХ 2026 | O424: =INDEX('список ID из СУЭ с должностями'!$A:$F,MATCH(E424,'список ID из СУЭ с должностями'!$B:$B,0),5) -> Инж смены
A425: 3 квартал 2026 | B425: Год + квартал | C425: 2026 | D425: 01.07.2026 - 30.09.2026 | E425: 57 | F425: Инженер | G425: Общество с ограниченной ответственностью "Томскнефтехим"/Направление Директора по производству/Производство мономеров/Смена 4 | H425: Базовые обязательства | I425: Потери сырья от ВО | J425: 0 | K425: Минимизация УМД | L425: Качественная | M425: Контракт | N425: ТНХ 2026 | O425: =INDEX('список ID из СУЭ с должностями'!$A:$F,MATCH(E425,'список ID из СУЭ с должностями'!$B:$B,0),5) -> Инж смены
A426: 3 квартал 2026 | B426: Год + квартал | C426: 2026 | D426: 01.07.2026 - 30.09.2026 | E426: 57 | F426: Инженер | G426: Общество с ограниченной ответственностью "Томскнефтехим"/Направление Директора по производству/Производство мономеров/Смена 4 | H426: Базовые обязательства | I426: Выполнение целей стратегии устойчивого развития: | J426: 1.1. Выбросы ЗВ в атмосферу не более 0,357 тыс.тн 2. Сбросы ЗВ в стоки не более 0,101 тыс. тн 3. Отходы на размещение не более 0,055 тыс. тн. | K426: Выполнение целей стратегии устойчивого развития, % Не менее 100 % | L426: Качественная | M426: Контракт | N426: ТНХ 2026 | O426: =INDEX('список ID из СУЭ с должностями'!$A:$F,MATCH(E426,'список ID из СУЭ с должностями'!$B:$B,0),5) -> Инж смены
A427: 3 квартал 2026 | B427: Год + квартал | C427: 2026 | D427: 01.07.2026 - 30.09.2026 | E427: 58 | F427: Химик | G427: Общество с ограниченной ответственностью "Томскнефтехим"/Служба главного технолога/Центральная заводская лаборатория/Смена 4 | H427: Базовые обязательства | I427: Реализация программы развития ПСС в ЦЗЛ на 2026г. | J427: Выполнение плана работ по ПСС в препараторской за 3 кв 2026 г. | K427: Обеспечить приживаемость Производственной системы | L427: Качественная | M427: Контракт | N427: ТНХ 2026 | O427: =INDEX('список ID из СУЭ с должностями'!$A:$F,MATCH(E427,'список ID из СУЭ с должностями'!$B:$B,0),5) -> 0
A428: 3 квартал 2026 | B428: Год + квартал | C428: 2026 | D428: 01.07.2026 - 30.09.2026 | E428: 58 | F428: Химик | G428: Общество с ограниченной ответственностью "Томскнефтехим"/Служба главного технолога/Центральная заводская лаборатория/Смена 4 | H428: Задачи с эффектом в текущем году | I428: Рациональное использование ресурсов ЦЗЛ | J428: Реактивы, материалы, посуда, оборудование используются по действующим методикам и правилам ЦЗЛ, вносятся предложения по улучшениям процессов | K428: Выполнение ключевых финансово-экономических показателей | L428: Качественная | M428: Контракт | N428: ТНХ 2026 | O428: =INDEX('список ID из СУЭ с должностями'!$A:$F,MATCH(E428,'список ID из СУЭ с должностями'!$B:$B,0),5) -> 0
A429: 3 квартал 2026 | B429: Год + квартал | C429: 2026 | D429: 01.07.2026 - 30.09.2026 | E429: 58 | F429: Химик | G429: Общество с ограниченной ответственностью "Томскнефтехим"/Служба главного технолога/Центральная заводская лаборатория/Смена 4 | H429: Базовые обязательства | I429: Развитие функциональных компетенций | J429: Прохождение обучения, получение допусков на вновь вводимом оборудовании. Обучение в рамках программ СИБУРИНТЕХ. | K429: Выполнение целей стратегии устойчивого развития, % Не менее 100 % | L429: Качественная | M429: Контракт | N429: ТНХ 2026 | O429: =INDEX('список ID из СУЭ с должностями'!$A:$F,MATCH(E429,'список ID из СУЭ с должностями'!$B:$B,0),5) -> 0
A430: 3 квартал 2026 | B430: Год + квартал | C430: 2026 | D430: 01.07.2026 - 30.09.2026 | E430: 58 | F430: Химик | G430: Общество с ограниченной ответственностью "Томскнефтехим"/Служба главного технолога/Центральная заводская лаборатория/Смена 4 | H430: Базовые обязательства | I430: Развитие технических компетенций | J430: Выполнение плана работы УОТ на 3 кв.2026г. | K430: Реализация производственного плана Не менее 426.1 тыс. тн | L430: Качественная | M430: Контракт | N430: ТНХ 2026 | O430: =INDEX('список ID из СУЭ с должностями'!$A:$F,MATCH(E430,'список ID из СУЭ с должностями'!$B:$B,0),5) -> 0
A431: 3 квартал 2026 | B431: Год + квартал | C431: 2026 | D431: 01.07.2026 - 30.09.2026 | E431: 58 | F431: Химик | G431: Общество с ограниченной ответственностью "Томскнефтехим"/Служба главного технолога/Центральная заводская лаборатория/Смена 4 | H431: Долгосрочные цели | I431: Развитие системы менеджмента | J431: Знать и соблюдать РК ЦЗЛ. Отсутствие замечаний по процедурам, действующим в ЦЗЛ. | K431: Реализация производственного плана Не менее 426.1 тыс. тн | L431: Качественная | M431: Контракт | N431: ТНХ 2026 | O431: =INDEX('список ID из СУЭ с должностями'!$A:$F,MATCH(E431,'список ID из СУЭ с должностями'!$B:$B,0),5) -> 0
A432: 3 квартал 2026 | B432: Год + квартал | C432: 2026 | D432: 01.07.2026 - 30.09.2026 | E432: 58 | F432: Химик | G432: Общество с ограниченной ответственностью "Томскнефтехим"/Служба главного технолога/Центральная заводская лаборатория/Смена 4 | H432: Базовые обязательства | I432: Вовлеченность в Чемпионаты по ОТ, Экологии | J432: С начала каждого месяца проводить не менее 1 ПАБ по ОТ, не менее 5 ЛО по ОТ( с подтвержденным средним риском за 3кв. 2 ЛО). Экология: не менее 5 ЛО, не менее 1 экомероприятия. | K432: Выполнение целей стратегии устойчивого развития, % Не менее 100 % | L432: Качественная | M432: Контракт | N432: ТНХ 2026 | O432: =INDEX('список ID из СУЭ с должностями'!$A:$F,MATCH(E432,'список ID из СУЭ с должностями'!$B:$B,0),5) -> 0
A433: 3 квартал 2026 | B433: Год + квартал | C433: 2026 | D433: 01.07.2026 - 30.09.2026 | E433: 58 | F433: Химик | G433: Общество с ограниченной ответственностью "Томскнефтехим"/Служба главного технолога/Центральная заводская лаборатория/Смена 4 | H433: Базовые обязательства | I433: Подача идей УМШ | J433: не менее 1 шт | K433: Обеспечить приживаемость Производственной системы | L433: Количественная | M433: Контракт | N433: ТНХ 2026 | O433: =INDEX('список ID из СУЭ с должностями'!$A:$F,MATCH(E433,'список ID из СУЭ с должностями'!$B:$B,0),5) -> 0
A434: 3 квартал 2026 | B434: Год + квартал | C434: 2026 | D434: 01.07.2026 - 30.09.2026 | E434: 58 | F434: Химик | G434: Общество с ограниченной ответственностью "Томскнефтехим"/Служба главного технолога/Центральная заводская лаборатория/Смена 4 | H434: Базовые обязательства | I434: Обеспечение выполнения аналитконтроля в зоне ответственности | J434: 100% выполнение ГАК, утвержденных ОПИ, согласованных заявок | K434: Минимизация потерь | L434: Качественная | M434: Контракт | N434: ТНХ 2026 | O434: =INDEX('список ID из СУЭ с должностями'!$A:$F,MATCH(E434,'список ID из СУЭ с должностями'!$B:$B,0),5) -> 0
A435: 3 квартал 2026 | B435: Год + квартал | C435: 2026 | D435: 01.07.2026 - 30.09.2026 | E435: 58 | F435: Химик | G435: Общество с ограниченной ответственностью "Томскнефтехим"/Служба главного технолога/Центральная заводская лаборатория/Смена 4 | H435: Задачи с эффектом в текущем году | I435: Безопасное проведение ОР в зоне функционала | J435: Безопасное проведение лабораторных работ, оперативная подготовка и передача пробоотборной тары, оперативная передача данных заказчику | K435: Минимизация травматизма (LTIF) | L435: Качественная | M435: Контракт | N435: ТНХ 2026 | O435: =INDEX('список ID из СУЭ с должностями'!$A:$F,MATCH(E435,'список ID из СУЭ с должностями'!$B:$B,0),5) -> 0
A436: 3 квартал 2026 | B436: Год + квартал | C436: 2026 | D436: 01.07.2026 - 30.09.2026 | E436: 58 | F436: Химик | G436: Общество с ограниченной ответственностью "Томскнефтехим"/Служба главного технолога/Центральная заводская лаборатория/Смена 4 | H436: Базовые обязательства | I436: Отсутствие претензий от внутренних заказчиков: оперативность и качество сервиса | J436: "0" подтвержденных претензий по качеству измерений и оперативности выполнения измерений | K436: Реализация производственного плана Не менее 426.1 тыс. тн | L436: Качественная | M436: Контракт | N436: ТНХ 2026 | O436: =INDEX('список ID из СУЭ с должностями'!$A:$F,MATCH(E436,'список ID из СУЭ с должностями'!$B:$B,0),5) -> 0
A437: 3 квартал 2026 | B437: Год + квартал | C437: 2026 | D437: 01.07.2026 - 30.09.2026 | E437: 59 | F437: Химик | G437: Общество с ограниченной ответственностью "Томскнефтехим"/Служба главного технолога/Центральная заводская лаборатория/Смена 1 | H437: Базовые обязательства | I437: Реализация программы развития ПСС в ЦЗЛ на 3 кв.2026г. | J437: Выполнение планов по сменам | K437: Обеспечить приживаемость Производственной системы | L437: Качественная | M437: Контракт | N437: ТНХ 2026 | O437: =INDEX('список ID из СУЭ с должностями'!$A:$F,MATCH(E437,'список ID из СУЭ с должностями'!$B:$B,0),5) -> 0
... A624: 3 квартал 2026 | B624: Год + квартал | C624: 2026 | D624: 01.07.2026 - 30.09.2026 | E624: 86 | F624: Руководитель ремонтного производства | G624: Общество с ограниченной ответственностью "Томскнефтехим"/Направление Главного инженера/Направление заместителя главного инженера/Ремонтное производство | H624: Базовые обязательства | I624: Подготовка и Выполнение остановочного ремонта согласно амбициозным срокам | J624: 1. 100% выполнение работ, влияющих на соблюдение межремонтного интервала в з.о. 2. Все работы в SAP закрыты, использованные материалы списаны до начала пусковых работ в з.о. 3.Вся документация (ИД, ЭД) заполнена до пуска оборудования 4. ОР проведён согласно амбициозных сроков (ПМ 25 дней, ПЭВД 21 день) в з.о. 5. Не зафиксировано происшествий по ОТ и ПБ и влияющих на ИА в з.о. 6. Дополнительный и внеплановый объем выполнен без влияния на сроки ОР в з.о. 7.Выполнение объема работ от замороженного 92% <Х<100 % в з.о. 8. Выполнение объема работ критического пути на 100% в з.о. 9. Потери ВПР в течение 20 суток после ОР в з.о. | K624: Успешное выполнение остановочного ремонта 2026 года | L624: Качественная | M624: Контракт | N624: ТНХ 2026 | O624: =INDEX('список ID из СУЭ с должностями'!$A:$F,MATCH(E624,'список ID из СУЭ с должностями'!$B:$B,0),5) -> 0
A625: 3 квартал 2026 | B625: Год + квартал | C625: 2026 | D625: 01.07.2026 - 30.09.2026 | E625: 87 | F625: Ведущий инженер по вибродиагностике | G625: Общество с ограниченной ответственностью "Томскнефтехим"/Направление Главного инженера/Служба управления надежностью/Лаборатория неразрушающего контроля и диагностики | H625: Базовые обязательства | I625: Минимизация травматизма (LTIF) | J625: 0 | K625: Минимизация травматизма (LTIF) | L625: Качественная | M625: Контракт | N625: ТНХ 2026 | O625: =INDEX('список ID из СУЭ с должностями'!$A:$F,MATCH(E625,'список ID из СУЭ с должностями'!$B:$B,0),5) -> 0
A626: 3 квартал 2026 | B626: Год + квартал | C626: 2026 | D626: 01.07.2026 - 30.09.2026 | E626: 87 | F626: Ведущий инженер по вибродиагностике | G626: Общество с ограниченной ответственностью "Томскнефтехим"/Направление Главного инженера/Служба управления надежностью/Лаборатория неразрушающего контроля и диагностики | H626: Базовые обязательства | I626: Восстановить точки замеров виб. на насосах тит.402, поз. Н-8, Н-9, Н-10, Н-75 | J626: Повышение точности сравнительно анализа вибрации | K626: Минимизация аварийности производственных объектов (ИА1) | L626: Качественная | M626: Контракт | N626: ТНХ 2026 | O626: =INDEX('список ID из СУЭ с должностями'!$A:$F,MATCH(E626,'список ID из СУЭ с должностями'!$B:$B,0),5) -> 0
A627: 3 квартал 2026 | B627: Год + квартал | C627: 2026 | D627: 01.07.2026 - 30.09.2026 | E627: 87 | F627: Ведущий инженер по вибродиагностике | G627: Общество с ограниченной ответственностью "Томскнефтехим"/Направление Главного инженера/Служба управления надежностью/Лаборатория неразрушающего контроля и диагностики | H627: Долгосрочные цели | I627: Оформление ПАБ | J627: не менее 15 штук | K627: Минимизация травматизма (LTIF) | L627: Количественная | M627: Контракт | N627: ТНХ 2026 | O627: =INDEX('список ID из СУЭ с должностями'!$A:$F,MATCH(E627,'список ID из СУЭ с должностями'!$B:$B,0),5) -> 0
A628: 3 квартал 2026 | B628: Год + квартал | C628: 2026 | D628: 01.07.2026 - 30.09.2026 | E628: 87 | F628: Ведущий инженер по вибродиагностике | G628: Общество с ограниченной ответственностью "Томскнефтехим"/Направление Главного инженера/Служба управления надежностью/Лаборатория неразрушающего контроля и диагностики | H628: Долгосрочные цели | I628: Мониторинг состояния резервуара Е-2 и оформление заключений за отчетный квартал | J628: Безаварийная эксплуатация резервуара ИХЭ | K628: Минимизация аварийности производственных объектов (ИА1) | L628: Качественная | M628: Контракт | N628: ТНХ 2026 | O628: =INDEX('список ID из СУЭ с должностями'!$A:$F,MATCH(E628,'список ID из СУЭ с должностями'!$B:$B,0),5) -> 0
A629: 3 квартал 2026 | B629: Год + квартал | C629: 2026 | D629: 01.07.2026 - 30.09.2026 | E629: 87 | F629: Ведущий инженер по вибродиагностике | G629: Общество с ограниченной ответственностью "Томскнефтехим"/Направление Главного инженера/Служба управления надежностью/Лаборатория неразрушающего контроля и диагностики | H629: Долгосрочные цели | I629: Выполнение задач экспертного сообщества КЦ | J629: Проведена защита на инженерном совете целевой инициативы по оснащению агрегатов системами вибромониторинга и вибродиагностики | K629: Развитие Производственной Системы и компетенций команды | L629: Качественная | M629: Контракт | N629: ФЭП 2026 | O629: =INDEX('список ID из СУЭ с должностями'!$A:$F,MATCH(E629,'список ID из СУЭ с должностями'!$B:$B,0),5) -> 0
A630: 3 квартал 2026 | B630: Год + квартал | C630: 2026 | D630: 01.07.2026 - 30.09.2026 | E630: 87 | F630: Ведущий инженер по вибродиагностике | G630: Общество с ограниченной ответственностью "Томскнефтехим"/Направление Главного инженера/Служба управления надежностью/Лаборатория неразрушающего контроля и диагностики | H630: Базовые обязательства | I630: Минимизация аварийности производственных объектов (ИА1) | J630: 0 | K630: Минимизация аварийности производственных объектов (ИА1) | L630: Качественная | M630: Контракт | N630: ТНХ 2026 | O630: =INDEX('список ID из СУЭ с должностями'!$A:$F,MATCH(E630,'список ID из СУЭ с должностями'!$B:$B,0),5) -> 0
A631: 3 квартал 2026 | B631: Год + квартал | C631: 2026 | D631: 01.07.2026 - 30.09.2026 | E631: 87 | F631: Ведущий инженер по вибродиагностике | G631: Общество с ограниченной ответственностью "Томскнефтехим"/Направление Главного инженера/Служба управления надежностью/Лаборатория неразрушающего контроля и диагностики | H631: Задачи с эффектом в текущем году | I631: Успешное выполнение работ в период ОР-26 | J631: Работы выполнены безопасно и в срок. | K631: Успешное выполнение остановочного ремонта 2026 года | L631: Качественная | M631: Контракт | N631: ТНХ 2026 | O631: =INDEX('список ID из СУЭ с должностями'!$A:$F,MATCH(E631,'список ID из СУЭ с должностями'!$B:$B,0),5) -> 0
A632: 3 квартал 2026 | B632: Год + квартал | C632: 2026 | D632: 01.07.2026 - 30.09.2026 | E632: 88 | F632: Ведущий инженер | G632: Общество с ограниченной ответственностью "Томскнефтехим"/Направление Главного инженера/Служба управления надежностью/Отдел технического надзора | H632: Базовые обязательства | I632: Проведение комплексной проверки на ЭП согласно графику | J632: 1) Обход с проведением осмотра 2) Обход с применением течеискателя 3) Ознакомление и согласование сроков устранения с ответственными 3) Внесение замечаний в систему Иди и смотри | K632: Проведение комплексной проверки ПМ, ЭП | L632: Качественная | M632: АР | N632: Рыбалов Иван Владимирович | O632: =INDEX('список ID из СУЭ с должностями'!$A:$F,MATCH(E632,'список ID из СУЭ с должностями'!$B:$B,0),5) -> 0
A633: 3 квартал 2026 | B633: Год + квартал | C633: 2026 | D633: 01.07.2026 - 30.09.2026 | E633: 88 | F633: Ведущий инженер | G633: Общество с ограниченной ответственностью "Томскнефтехим"/Направление Главного инженера/Служба управления надежностью/Отдел технического надзора | H633: Базовые обязательства | I633: Проведение комплексной проверки на ПМ согласно графику | J633: 1) Обход с проведением осмотра 2) Обход с применением течеискателя 3) Ознакомление и согласование сроков устранения с ответственными 3) Внесение замечаний в систему Иди и смотри | K633: Проведение комплексной проверки ПМ, ЭП | L633: Качественная | M633: АР | N633: Рыбалов Иван Владимирович | O633: =INDEX('список ID из СУЭ с должностями'!$A:$F,MATCH(E633,'список ID из СУЭ с должностями'!$B:$B,0),5) -> 0
A634: 3 квартал 2026 | B634: Год + квартал | C634: 2026 | D634: 01.07.2026 - 30.09.2026 | E634: 88 | F634: Ведущий инженер | G634: Общество с ограниченной ответственностью "Томскнефтехим"/Направление Главного инженера/Служба управления надежностью/Отдел технического надзора | H634: Базовые обязательства | I634: Минимизация травматизма. Отсутствие НС по СУН | J634: не более 0 . | K634: Минимизация травматизма (LTIF) | L634: Количественная | M634: Контракт | N634: ТНХ 2026 | O634: =INDEX('список ID из СУЭ с должностями'!$A:$F,MATCH(E634,'список ID из СУЭ с должностями'!$B:$B,0),5) -> 0
A635: 3 квартал 2026 | B635: Год + квартал | C635: 2026 | D635: 01.07.2026 - 30.09.2026 | E635: 88 | F635: Ведущий инженер | G635: Общество с ограниченной ответственностью "Томскнефтехим"/Направление Главного инженера/Служба управления надежностью/Отдел технического надзора | H635: Задачи с эффектом в текущем году | I635: Организация проведения работ по ЭПБ в ОР 2026 | J635: Выполнение работ по ЭПБ 2026 в ОР 2026 согласно графика | K635: Успешное выполнение остановочного ремонта 2026 года | L635: Качественная | M635: Контракт | N635: ТНХ 2026 | O635: =INDEX('список ID из СУЭ с должностями'!$A:$F,MATCH(E635,'список ID из СУЭ с должностями'!$B:$B,0),5) -> 0
A636: 3 квартал 2026 | B636: Год + квартал | C636: 2026 | D636: 01.07.2026 - 30.09.2026 | E636: 88 | F636: Ведущий инженер | G636: Общество с ограниченной ответственностью "Томскнефтехим"/Направление Главного инженера/Служба управления надежностью/Отдел технического надзора | H636: Базовые обязательства | I636: Организация проведения ЭПБ до ОР 2026 | J636: 1) Организация сбора технической и эксплуатационной документации. 2) Организация в предоставлении схем НК под зачистку. 3) Соблюдение дорожной карты. 4) Контроль соблюдения сроков согласно дорожной карты. | K636: Минимизация аварийности производственных объектов (ИА1) | L636: Качественная | M636: Контракт | N636: ТНХ 2026 | O636: =INDEX('список ID из СУЭ с должностями'!$A:$F,MATCH(E636,'список ID из СУЭ с должностями'!$B:$B,0),5) -> 0
A637: 3 квартал 2026 | B637: Год + квартал | C637: 2026 | D637: 01.07.2026 - 30.09.2026 | E637: 89 | F637: Инженер | G637: Общество с ограниченной ответственностью "Томскнефтехим"/Направление Директора по производству/Производство мономеров/Смена 3/Установка пиролиза углеводородов нефти | H637: Базовые обязательства | I637: снижение НАК | J637: не более 1579 шт | K637: Повышение производственной эффективности | L637: Количественная | M637: Контракт | N637: ТНХ 2026 | O637: =INDEX('список ID из СУЭ с должностями'!$A:$F,MATCH(E637,'список ID из СУЭ с должностями'!$B:$B,0),5) -> Инж смены
A638: 3 квартал 2026 | B638: Год + квартал | C638: 2026 | D638: 01.07.2026 - 30.09.2026 | E638: 89 | F638: Инженер | G638: Общество с ограниченной ответственностью "Томскнефтехим"/Направление Директора по производству/Производство мономеров/Смена 3/Установка пиролиза углеводородов нефти | H638: Базовые обязательства | I638: Эффективность работы ЭКОНС | J638: не менее 81 % | K638: Повышение производственной эффективности | L638: Количественная | M638: Контракт | N638: ТНХ 2026 | O638: =INDEX('список ID из СУЭ с должностями'!$A:$F,MATCH(E638,'список ID из СУЭ с должностями'!$B:$B,0),5) -> Инж смены
A639: 3 квартал 2026 | B639: Год + квартал | C639: 2026 | D639: 01.07.2026 - 30.09.2026 | E639: 89 | F639: Инженер | G639: Общество с ограниченной ответственностью "Томскнефтехим"/Направление Директора по производству/Производство мономеров/Смена 3/Установка пиролиза углеводородов нефти | H639: Базовые обязательства | I639: Снижение сигнализаций | J639: не более 16364 шт | K639: Повышение производственной эффективности | L639: Количественная | M639: Контракт | N639: ТНХ 2026 | O639: =INDEX('список ID из СУЭ с должностями'!$A:$F,MATCH(E639,'список ID из СУЭ с должностями'!$B:$B,0),5) -> Инж смены
A640: 3 квартал 2026 | B640: Год + квартал | C640: 2026 | D640: 01.07.2026 - 30.09.2026 | E640: 89 | F640: Инженер | G640: Общество с ограниченной ответственностью "Томскнефтехим"/Направление Директора по производству/Производство мономеров/Смена 3/Установка пиролиза углеводородов нефти | H640: Базовые обязательства | I640: Снижение нарушений НТР | J640: не более 27096 шт | K640: Повышение производственной эффективности | L640: Количественная | M640: Контракт | N640: ТНХ 2026 | O640: =INDEX('список ID из СУЭ с должностями'!$A:$F,MATCH(E640,'список ID из СУЭ с должностями'!$B:$B,0),5) -> Инж смены
A641: 3 квартал 2026 | B641: Год + квартал | C641: 2026 | D641: 01.07.2026 - 30.09.2026 | E641: 89 | F641: Инженер | G641: Общество с ограниченной ответственностью "Томскнефтехим"/Направление Директора по производству/Производство мономеров/Смена 3/Установка пиролиза углеводородов нефти | H641: Базовые обязательства | I641: Количество пультовых операций в зоне ответственности | J641: не более 30600 шт | K641: Повышение производственной эффективности | L641: Количественная | M641: Контракт | N641: ТНХ 2026 | O641: =INDEX('список ID из СУЭ с должностями'!$A:$F,MATCH(E641,'список ID из СУЭ с должностями'!$B:$B,0),5) -> Инж смены
A642: 3 квартал 2026 | B642: Год + квартал | C642: 2026 | D642: 01.07.2026 - 30.09.2026 | E642: 89 | F642: Инженер | G642: Общество с ограниченной ответственностью "Томскнефтехим"/Направление Директора по производству/Производство мономеров/Смена 3/Установка пиролиза углеводородов нефти | H642: Базовые обязательства | I642: Эффективность работы СУУТП (АРС) | J642: не менее 93 % | K642: Повышение производственной эффективности | L642: Количественная | M642: Контракт | N642: ТНХ 2026 | O642: =INDEX('список ID из СУЭ с должностями'!$A:$F,MATCH(E642,'список ID из СУЭ с должностями'!$B:$B,0),5) -> Инж смены
...

Sheet Лист1
A1: ТН сотрудника | B1: ИД сотрудника
A2: 23017551 | B2: 1
A3: 23000162 | B3: 2
A4: 23000229 | B4: 3
A5: 23000379 | B5: 4
A6: 23000394 | B6: 5
A7: 23000479 | B7: 6
A8: 23000507 | B8: 7
A9: 23000508 | B9: 8
A10: 23000797 | B10: 9
A11: 23001069 | B11: 10
A12: 23001120 | B12: 11
A13: 23001348 | B13: 12
... A548: 22077015 | B548: 547

Sheet список ID из СУЭ с должностями
A1: Принадлежность к СДП | B1: ID сотрудника | C1: Должность | D1: Подразделение
A2: =IF(ISNA(INDEX('ID относящиеся у производству'!A:A,MATCH(B2,'ID относящиеся у производству'!A:A,0),1))=TRUE,"НЕТ","ДА") -> НЕТ | B2: 1 | C2: Заместитель главного инженера | D2: Общество с ограниченной ответственностью "Томскнефтехим"/Направление Главного инженера/Направление заместителя главного инженера
A3: =IF(ISNA(INDEX('ID относящиеся у производству'!A:A,MATCH(B3,'ID относящиеся у производству'!A:A,0),1))=TRUE,"НЕТ","ДА") -> ДА | B3: 2 | C3: Начальник смены производства | D3: Общество с ограниченной ответственностью "Томскнефтехим"/Направление Директора по производству/Производство полиэтилена/Смена 3 | E3: НС | F3: СДП
A4: =IF(ISNA(INDEX('ID относящиеся у производству'!A:A,MATCH(B4,'ID относящиеся у производству'!A:A,0),1))=TRUE,"НЕТ","ДА") -> НЕТ | B4: 3 | C4: Эксперт | D4: Общество с ограниченной ответственностью "Томскнефтехим"/Направление Директора по управлению персоналом
A5: =IF(ISNA(INDEX('ID относящиеся у производству'!A:A,MATCH(B5,'ID относящиеся у производству'!A:A,0),1))=TRUE,"НЕТ","ДА") -> НЕТ | B5: 4 | C5: Ведущий специалист | D5: Общество с ограниченной ответственностью "Томскнефтехим"/Направление Главного инженера/Направление заместителя главного инженера/Служба управления основными фондами/Отдел планирования и контроля
A6: =IF(ISNA(INDEX('ID относящиеся у производству'!A:A,MATCH(B6,'ID относящиеся у производству'!A:A,0),1))=TRUE,"НЕТ","ДА") -> НЕТ | B6: 5 | C6: Эксперт | D6: Общество с ограниченной ответственностью "Томскнефтехим"/Направление Главного инженера/Направление заместителя главного инженера/Управление материально-техническим обеспечением производства/Отдел закупок материально-технических ресурсов и реализации невостребованного имущества
A7: =IF(ISNA(INDEX('ID относящиеся у производству'!A:A,MATCH(B7,'ID относящиеся у производству'!A:A,0),1))=TRUE,"НЕТ","ДА") -> НЕТ | B7: 6 | C7: Специалист | D7: Общество с ограниченной ответственностью "Томскнефтехим"/Направление Главного инженера/Направление заместителя главного инженера/Управление материально-техническим обеспечением производства/Складское хозяйство
A8: =IF(ISNA(INDEX('ID относящиеся у производству'!A:A,MATCH(B8,'ID относящиеся у производству'!A:A,0),1))=TRUE,"НЕТ","ДА") -> НЕТ | B8: 7 | C8: Инженер по метрологии | D8: Общество с ограниченной ответственностью "Томскнефтехим"/Направление Главного инженера/Направление заместителя главного инженера/Ремонтное производство/Ремонтное производство по ТОиР КИПиА, АСУ ТП Производств: мономеров, полиэтилена, полипропилена/Метрологическая лаборатория
A9: =IF(ISNA(INDEX('ID относящиеся у производству'!A:A,MATCH(B9,'ID относящиеся у производству'!A:A,0),1))=TRUE,"НЕТ","ДА") -> НЕТ | B9: 8 | C9: Инженер по метрологии | D9: Общество с ограниченной ответственностью "Томскнефтехим"/Направление Главного инженера/Направление заместителя главного инженера/Ремонтное производство/Ремонтное производство по ТОиР КИПиА, АСУ ТП Производств: мономеров, полиэтилена, полипропилена/Метрологическая лаборатория
A10: =IF(ISNA(INDEX('ID относящиеся у производству'!A:A,MATCH(B10,'ID относящиеся у производству'!A:A,0),1))=TRUE,"НЕТ","ДА") -> НЕТ | B10: 9 | C10: Химик | D10: Общество с ограниченной ответственностью "Томскнефтехим"/Служба главного технолога/Центральная заводская лаборатория/Смена 1
A11: =IF(ISNA(INDEX('ID относящиеся у производству'!A:A,MATCH(B11,'ID относящиеся у производству'!A:A,0),1))=TRUE,"НЕТ","ДА") -> ДА | B11: 10 | C11: Эксперт | D11: Общество с ограниченной ответственностью "Томскнефтехим"/Направление Директора по производству/Производство полиэтилена
A12: =IF(ISNA(INDEX('ID относящиеся у производству'!A:A,MATCH(B12,'ID относящиеся у производству'!A:A,0),1))=TRUE,"НЕТ","ДА") -> ДА | B12: 11 | C12: Инженер | D12: Общество с ограниченной ответственностью "Томскнефтехим"/Направление Директора по производству/Производство полипропилена/Смена 2 | E12: Инж смены | F12: СДП
A13: =IF(ISNA(INDEX('ID относящиеся у производству'!A:A,MATCH(B13,'ID относящиеся у производству'!A:A,0),1))=TRUE,"НЕТ","ДА") -> НЕТ | B13: 12 | C13: Химик | D13: Общество с ограниченной ответственностью "Томскнефтехим"/Служба главного технолога/Центральная заводская лаборатория/Смена 4
A14: =IF(ISNA(INDEX('ID относящиеся у производству'!A:A,MATCH(B14,'ID относящиеся у производству'!A:A,0),1))=TRUE,"НЕТ","ДА") -> НЕТ | B14: 13 | C14: Химик | D14: Общество с ограниченной ответственностью "Томскнефтехим"/Служба главного технолога/Центральная заводская лаборатория/Смена 3
A15: =IF(ISNA(INDEX('ID относящиеся у производству'!A:A,MATCH(B15,'ID относящиеся у производству'!A:A,0),1))=TRUE,"НЕТ","ДА") -> НЕТ | B15: 14 | C15: Ведущий инженер-химик | D15: Общество с ограниченной ответственностью "Томскнефтехим"/Служба главного технолога/Центральная заводская лаборатория
A16: =IF(ISNA(INDEX('ID относящиеся у производству'!A:A,MATCH(B16,'ID относящиеся у производству'!A:A,0),1))=TRUE,"НЕТ","ДА") -> ДА | B16: 15 | C16: Инженер по подготовке производства | D16: Общество с ограниченной ответственностью "Томскнефтехим"/Направление Директора по производству/Производство полипропилена/Установка полимеризации пропилена | E16: ИПП | F16: СДП
A17: =IF(ISNA(INDEX('ID относящиеся у производству'!A:A,MATCH(B17,'ID относящиеся у производству'!A:A,0),1))=TRUE,"НЕТ","ДА") -> НЕТ | B17: 16 | C17: Старший химик | D17: Общество с ограниченной ответственностью "Томскнефтехим"/Служба главного технолога/Центральная заводская лаборатория
A18: =IF(ISNA(INDEX('ID относящиеся у производству'!A:A,MATCH(B18,'ID относящиеся у производству'!A:A,0),1))=TRUE,"НЕТ","ДА") -> НЕТ | B18: 17 | C18: Ведущий специалист | D18: Общество с ограниченной ответственностью "Томскнефтехим"/Направление Главного инженера/Направление заместителя главного инженера/Служба управления основными фондами/Отдел планирования и контроля
A19: =IF(ISNA(INDEX('ID относящиеся у производству'!A:A,MATCH(B19,'ID относящиеся у производству'!A:A,0),1))=TRUE,"НЕТ","ДА") -> ДА | B19: 18 | C19: Ведущий инженер | D19: Общество с ограниченной ответственностью "Томскнефтехим"/Направление Директора по производству/Энергопроизводство/Установка теплопароснабжения | E19: ВИП | F19: СДП
A20: =IF(ISNA(INDEX('ID относящиеся у производству'!A:A,MATCH(B20,'ID относящиеся у производству'!A:A,0),1))=TRUE,"НЕТ","ДА") -> НЕТ | B20: 19 | C20: Инженер | D20: Общество с ограниченной ответственностью "Томскнефтехим"/Направление Главного инженера/Направление заместителя главного инженера/Ремонтное производство/Ремонтное производство по изготовлению/Отдел технического контроля
A21: =IF(ISNA(INDEX('ID относящиеся у производству'!A:A,MATCH(B21,'ID относящиеся у производству'!A:A,0),1))=TRUE,"НЕТ","ДА") -> НЕТ | B21: 20 | C21: Менеджер | D21: Общество с ограниченной ответственностью "Томскнефтехим"/Направление Главного инженера/Направление заместителя главного инженера/Управление материально-техническим обеспечением производства/Отдел закупок материально-технических ресурсов и реализации невостребованного имущества
A22: =IF(ISNA(INDEX('ID относящиеся у производству'!A:A,MATCH(B22,'ID относящиеся у производству'!A:A,0),1))=TRUE,"НЕТ","ДА") -> НЕТ | B22: 21 | C22: Инженер-механик | D22: Общество с ограниченной ответственностью "Томскнефтехим"/Направление Первого заместителя Генерального директора – Главного инженера/Служба управления основными фондами/Отдел технического обслуживания и ремонтов/Техническое обслуживание и ремонты Производства углеводородов и сырья для пиролиза
A23: =IF(ISNA(INDEX('ID относящиеся у производству'!A:A,MATCH(B23,'ID относящиеся у производству'!A:A,0),1))=TRUE,"НЕТ","ДА") -> ДА | B23: 22 | C23: Специалист | D23: Общество с ограниченной ответственностью "Томскнефтехим"/Направление Директора по производству/Производство полиэтилена
A24: =IF(ISNA(INDEX('ID относящиеся у производству'!A:A,MATCH(B24,'ID относящиеся у производству'!A:A,0),1))=TRUE,"НЕТ","ДА") -> НЕТ | B24: 23 | C24: Инженер по качеству испытаний | D24: Общество с ограниченной ответственностью "Томскнефтехим"/Служба главного технолога/Центральная заводская лаборатория
A25: =IF(ISNA(INDEX('ID относящиеся у производству'!A:A,MATCH(B25,'ID относящиеся у производству'!A:A,0),1))=TRUE,"НЕТ","ДА") -> НЕТ | B25: 24 | C25: Инженер по автоматизации | D25: Общество с ограниченной ответственностью "Томскнефтехим"/Направление Главного инженера/Направление заместителя главного инженера/Служба управления основными фондами/Отдел технического обслуживания и ремонтов/Техническое обслуживание и ремонты Производства полипропилена
A26: =IF(ISNA(INDEX('ID относящиеся у производству'!A:A,MATCH(B26,'ID относящиеся у производству'!A:A,0),1))=TRUE,"НЕТ","ДА") -> НЕТ | B26: 25 | C26: Эксперт | D26: Общество с ограниченной ответственностью "Томскнефтехим"/Направление Главного инженера/Направление заместителя главного инженера/Служба управления основными фондами/Отдел проектирования
A27: =IF(ISNA(INDEX('ID относящиеся у производству'!A:A,MATCH(B27,'ID относящиеся у производству'!A:A,0),1))=TRUE,"НЕТ","ДА") -> НЕТ | B27: 26 | C27: Главный эксперт | D27: Общество с ограниченной ответственностью "Томскнефтехим"/Направление Главного инженера/Служба управления надежностью
A28: =IF(ISNA(INDEX('ID относящиеся у производству'!A:A,MATCH(B28,'ID относящиеся у производству'!A:A,0),1))=TRUE,"НЕТ","ДА") -> НЕТ | B28: 27 | C28: Ведущий инженер-технолог | D28: Общество с ограниченной ответственностью "Томскнефтехим"/Служба главного технолога/Отдел технологии и развития
A29: =IF(ISNA(INDEX('ID относящиеся у производству'!A:A,MATCH(B29,'ID относящиеся у производству'!A:A,0),1))=TRUE,"НЕТ","ДА") -> НЕТ | B29: 28 | C29: Инженер-технолог | D29: Общество с ограниченной ответственностью "Томскнефтехим"/Служба главного технолога/Отдел качества, стандартизации и технического регулирования
A30: =IF(ISNA(INDEX('ID относящиеся у производству'!A:A,MATCH(B30,'ID относящиеся у производству'!A:A,0),1))=TRUE,"НЕТ","ДА") -> НЕТ | B30: 29 | C30: Химик | D30: Общество с ограниченной ответственностью "Томскнефтехим"/Служба главного технолога/Центральная заводская лаборатория/Смена 2
A31: =IF(ISNA(INDEX('ID относящиеся у производству'!A:A,MATCH(B31,'ID относящиеся у производству'!A:A,0),1))=TRUE,"НЕТ","ДА") -> НЕТ | B31: 30 | C31: Инженер-технолог | D31: Общество с ограниченной ответственностью "Томскнефтехим"/Направление Главного инженера/Направление заместителя главного инженера/Ремонтное производство/Ремонтное производство по изготовлению
... A41: =IF(ISNA(INDEX('ID относящиеся у производству'!A:A,MATCH(B41,'ID относящиеся у производству'!A:A,0),1))=TRUE,"НЕТ","ДА") -> НЕТ | B41: 40 | C41: Специалист | D41: Общество с ограниченной ответственностью "Томскнефтехим"/Направление Главного инженера/Направление заместителя главного инженера/Управление материально-техническим обеспечением производства/Складское хозяйство
A42: =IF(ISNA(INDEX('ID относящиеся у производству'!A:A,MATCH(B42,'ID относящиеся у производству'!A:A,0),1))=TRUE,"НЕТ","ДА") -> ДА | B42: 41 | C42: Инженер по планированию и ресурсному обеспечению | D42: Общество с ограниченной ответственностью "Томскнефтехим"/Направление Директора по производству/Энергопроизводство | E42: ИПРО | F42: СДП
A43: =IF(ISNA(INDEX('ID относящиеся у производству'!A:A,MATCH(B43,'ID относящиеся у производству'!A:A,0),1))=TRUE,"НЕТ","ДА") -> НЕТ | B43: 42 | C43: Начальник отдела | D43: Общество с ограниченной ответственностью "Томскнефтехим"/Направление Главного инженера/Направление заместителя главного инженера/Ремонтное производство/Ремонтное производство по изготовлению/Отдел технического контроля
A44: =IF(ISNA(INDEX('ID относящиеся у производству'!A:A,MATCH(B44,'ID относящиеся у производству'!A:A,0),1))=TRUE,"НЕТ","ДА") -> ДА | B44: 43 | C44: Инженер | D44: Общество с ограниченной ответственностью "Томскнефтехим"/Направление Директора по производству/Производство мономеров/Смена 4/Установка пиролиза углеводородов нефти | E44: Инж смены | F44: СДП
A45: =IF(ISNA(INDEX('ID относящиеся у производству'!A:A,MATCH(B45,'ID относящиеся у производству'!A:A,0),1))=TRUE,"НЕТ","ДА") -> НЕТ | B45: 44 | C45: Диспетчер | D45: Общество с ограниченной ответственностью "Томскнефтехим"/Производственно-диспетчерское управление
A46: =IF(ISNA(INDEX('ID относящиеся у производству'!A:A,MATCH(B46,'ID относящиеся у производству'!A:A,0),1))=TRUE,"НЕТ","ДА") -> НЕТ | B46: 45 | C46: Старший химик | D46: Общество с ограниченной ответственностью "Томскнефтехим"/Служба главного технолога/Центральная заводская лаборатория
A47: =IF(ISNA(INDEX('ID относящиеся у производству'!A:A,MATCH(B47,'ID относящиеся у производству'!A:A,0),1))=TRUE,"НЕТ","ДА") -> ДА | B47: 46 | C47: Инженер по планированию и ресурсному обеспечению | D47: Общество с ограниченной ответственностью "Томскнефтехим"/Направление Директора по производству/Производство мономеров | E47: ИПРО | F47: СДП
A48: =IF(ISNA(INDEX('ID относящиеся у производству'!A:A,MATCH(B48,'ID относящиеся у производству'!A:A,0),1))=TRUE,"НЕТ","ДА") -> НЕТ | B48: 47 | C48: Диспетчер | D48: Общество с ограниченной ответственностью "Томскнефтехим"/Производственно-диспетчерское управление
A49: =IF(ISNA(INDEX('ID относящиеся у производству'!A:A,MATCH(B49,'ID относящиеся у производству'!A:A,0),1))=TRUE,"НЕТ","ДА") -> НЕТ | B49: 48 | C49: Химик | D49: Общество с ограниченной ответственностью "Томскнефтехим"/Служба главного технолога/Центральная заводская лаборатория/Смена 2
A50: =IF(ISNA(INDEX('ID относящиеся у производству'!A:A,MATCH(B50,'ID относящиеся у производству'!A:A,0),1))=TRUE,"НЕТ","ДА") -> НЕТ | B50: 49 | C50: Старший химик | D50: Общество с ограниченной ответственностью "Томскнефтехим"/Служба главного технолога/Центральная заводская лаборатория
A51: =IF(ISNA(INDEX('ID относящиеся у производству'!A:A,MATCH(B51,'ID относящиеся у производству'!A:A,0),1))=TRUE,"НЕТ","ДА") -> ДА | B51: 50 | C51: Инженер | D51: Общество с ограниченной ответственностью "Томскнефтехим"/Направление Директора по производству/Производство мономеров/Смена 1/Установка пиролиза углеводородов нефти | E51: Инж смены | F51: СДП
A52: =IF(ISNA(INDEX('ID относящиеся у производству'!A:A,MATCH(B52,'ID относящиеся у производству'!A:A,0),1))=TRUE,"НЕТ","ДА") -> НЕТ | B52: 51 | C52: Ведущий инженер по исследованию металлов | D52: Общество с ограниченной ответственностью "Томскнефтехим"/Направление Главного инженера/Служба управления надежностью/Лаборатория неразрушающего контроля и диагностики
A53: =IF(ISNA(INDEX('ID относящиеся у производству'!A:A,MATCH(B53,'ID относящиеся у производству'!A:A,0),1))=TRUE,"НЕТ","ДА") -> НЕТ | B53: 52 | C53: Химик | D53: Общество с ограниченной ответственностью "Томскнефтехим"/Служба главного технолога/Центральная заводская лаборатория/Смена 1
A54: =IF(ISNA(INDEX('ID относящиеся у производству'!A:A,MATCH(B54,'ID относящиеся у производству'!A:A,0),1))=TRUE,"НЕТ","ДА") -> ДА | B54: 53 | C54: Эксперт | D54: Общество с ограниченной ответственностью "Томскнефтехим"/Направление Директора по производству/Производство углеводородов и сырья для пиролиза
A55: =IF(ISNA(INDEX('ID относящиеся у производству'!A:A,MATCH(B55,'ID относящиеся у производству'!A:A,0),1))=TRUE,"НЕТ","ДА") -> НЕТ | B55: 54 | C55: Старший химик | D55: Общество с ограниченной ответственностью "Томскнефтехим"/Служба главного технолога/Центральная заводская лаборатория
A56: =IF(ISNA(INDEX('ID относящиеся у производству'!A:A,MATCH(B56,'ID относящиеся у производству'!A:A,0),1))=TRUE,"НЕТ","ДА") -> ДА | B56: 55 | C56: Инженер | D56: Общество с ограниченной ответственностью "Томскнефтехим"/Направление Директора по производству/Производство мономеров/Смена 2/Установка пиролиза углеводородов нефти | E56: Инж смены | F56: СДП
A57: =IF(ISNA(INDEX('ID относящиеся у производству'!A:A,MATCH(B57,'ID относящиеся у производству'!A:A,0),1))=TRUE,"НЕТ","ДА") -> НЕТ | B57: 56 | C57: Инженер по вибродиагностике | D57: Общество с ограниченной ответственностью "Томскнефтехим"/Направление Главного инженера/Служба управления надежностью/Лаборатория неразрушающего контроля и диагностики
A58: =IF(ISNA(INDEX('ID относящиеся у производству'!A:A,MATCH(B58,'ID относящиеся у производству'!A:A,0),1))=TRUE,"НЕТ","ДА") -> ДА | B58: 57 | C58: Инженер | D58: Общество с ограниченной ответственностью "Томскнефтехим"/Направление Директора по производству/Производство мономеров/Смена 4 | E58: Инж смены | F58: СДП
A59: =IF(ISNA(INDEX('ID относящиеся у производству'!A:A,MATCH(B59,'ID относящиеся у производству'!A:A,0),1))=TRUE,"НЕТ","ДА") -> НЕТ | B59: 58 | C59: Химик | D59: Общество с ограниченной ответственностью "Томскнефтехим"/Служба главного технолога/Центральная заводская лаборатория/Смена 4
A60: =IF(ISNA(INDEX('ID относящиеся у производству'!A:A,MATCH(B60,'ID относящиеся у производству'!A:A,0),1))=TRUE,"НЕТ","ДА") -> НЕТ | B60: 59 | C60: Химик | D60: Общество с ограниченной ответственностью "Томскнефтехим"/Служба главного технолога/Центральная заводская лаборатория/Смена 1
A61: =IF(ISNA(INDEX('ID относящиеся у производству'!A:A,MATCH(B61,'ID относящиеся у производству'!A:A,0),1))=TRUE,"НЕТ","ДА") -> НЕТ | B61: 60 | C61: Эксперт | D61: Общество с ограниченной ответственностью "Томскнефтехим"/Трудовое долголетие/Направление Директора по производству
A62: =IF(ISNA(INDEX('ID относящиеся у производству'!A:A,MATCH(B62,'ID относящиеся у производству'!A:A,0),1))=TRUE,"НЕТ","ДА") -> НЕТ | B62: 61 | C62: Диспетчер | D62: Общество с ограниченной ответственностью "Томскнефтехим"/Производственно-диспетчерское управление
A63: =IF(ISNA(INDEX('ID относящиеся у производству'!A:A,MATCH(B63,'ID относящиеся у производству'!A:A,0),1))=TRUE,"НЕТ","ДА") -> НЕТ | B63: 62 | C63: Эксперт | D63: Общество с ограниченной ответственностью "Томскнефтехим"/Производственно-диспетчерское управление
A64: =IF(ISNA(INDEX('ID относящиеся у производству'!A:A,MATCH(B64,'ID относящиеся у производству'!A:A,0),1))=TRUE,"НЕТ","ДА") -> НЕТ | B64: 63 | C64: Инженер по ресурсному планированию | D64: Общество с ограниченной ответственностью "Томскнефтехим"/Направление Главного инженера/Направление заместителя главного инженера/Служба управления основными фондами/Отдел технического обслуживания и ремонтов/Планирование
A65: =IF(ISNA(INDEX('ID относящиеся у производству'!A:A,MATCH(B65,'ID относящиеся у производству'!A:A,0),1))=TRUE,"НЕТ","ДА") -> НЕТ | B65: 64 | C65: Эксперт | D65: Общество с ограниченной ответственностью "Томскнефтехим"/Управление логистики
A66: =IF(ISNA(INDEX('ID относящиеся у производству'!A:A,MATCH(B66,'ID относящиеся у производству'!A:A,0),1))=TRUE,"НЕТ","ДА") -> НЕТ | B66: 65 | C66: Эксперт | D66: Общество с ограниченной ответственностью "Томскнефтехим"/Направление Директора по управлению персоналом
A67: =IF(ISNA(INDEX('ID относящиеся у производству'!A:A,MATCH(B67,'ID относящиеся у производству'!A:A,0),1))=TRUE,"НЕТ","ДА") -> НЕТ | B67: 66 | C67: Старший инженер по планированию | D67: Общество с ограниченной ответственностью "Томскнефтехим"/Направление Главного инженера/Направление заместителя главного инженера/Служба управления основными фондами/Отдел технического обслуживания и ремонтов/Планирование
A68: =IF(ISNA(INDEX('ID относящиеся у производству'!A:A,MATCH(B68,'ID относящиеся у производству'!A:A,0),1))=TRUE,"НЕТ","ДА") -> ДА | B68: 67 | C68: Ведущий инженер по учету энергоресурсов | D68: Общество с ограниченной ответственностью "Томскнефтехим"/Направление Директора по производству/Отдел управления энергоресурсами
A69: =IF(ISNA(INDEX('ID относящиеся у производству'!A:A,MATCH(B69,'ID относящиеся у производству'!A:A,0),1))=TRUE,"НЕТ","ДА") -> НЕТ | B69: 68 | C69: Инженер | D69: Общество с ограниченной ответственностью "Томскнефтехим"/Направление Главного инженера/Направление заместителя главного инженера/Ремонтное производство/Ремонтное производство по ремонту технологических установок Производств: мономеров, полиэтилена, полипропилена
A70: =IF(ISNA(INDEX('ID относящиеся у производству'!A:A,MATCH(B70,'ID относящиеся у производству'!A:A,0),1))=TRUE,"НЕТ","ДА") -> НЕТ | B70: 69 | C70: Старший инженер по планированию | D70: Общество с ограниченной ответственностью "Томскнефтехим"/Направление Главного инженера/Направление заместителя главного инженера/Служба управления основными фондами/Отдел технического обслуживания и ремонтов/Планирование
A71: =IF(ISNA(INDEX('ID относящиеся у производству'!A:A,MATCH(B71,'ID относящиеся у производству'!A:A,0),1))=TRUE,"НЕТ","ДА") -> НЕТ | B71: 70 | C71: Эксперт | D71: Общество с ограниченной ответственностью "Томскнефтехим"/Направление Главного инженера/Направление заместителя главного инженера/Ремонтное производство/Ремонтное производство по ремонту технологического оборудования Производств: мономеров, полиэтилена, полипропилена/Участок по ремонту технологического оборудования Производства полиэтилена
A72: =IF(ISNA(INDEX('ID относящиеся у производству'!A:A,MATCH(B72,'ID относящиеся у производству'!A:A,0),1))=TRUE,"НЕТ","ДА") -> ДА | B72: 71 | C72: Инженер | D72: Общество с ограниченной ответственностью "Томскнефтехим"/Направление Директора по производству/Производство мономеров/Смена 2 | E72: Инж смены | F72: СДП
A73: =IF(ISNA(INDEX('ID относящиеся у производству'!A:A,MATCH(B73,'ID относящиеся у производству'!A:A,0),1))=TRUE,"НЕТ","ДА") -> НЕТ | B73: 72 | C73: Инженер-механик | D73: Общество с ограниченной ответственностью "Томскнефтехим"/Направление Главного инженера/Направление заместителя главного инженера/Служба управления основными фондами/Отдел технического обслуживания и ремонтов/Техническое обслуживание и ремонты Производства полиэтилена
A74: =IF(ISNA(INDEX('ID относящиеся у производству'!A:A,MATCH(B74,'ID относящиеся у производству'!A:A,0),1))=TRUE,"НЕТ","ДА") -> НЕТ | B74: 73 | C74: Химик | D74: Общество с ограниченной ответственностью "Томскнефтехим"/Служба главного технолога/Центральная заводская лаборатория/Смена 3
A75: =IF(ISNA(INDEX('ID относящиеся у производству'!A:A,MATCH(B75,'ID относящиеся у производству'!A:A,0),1))=TRUE,"НЕТ","ДА") -> ДА | B75: 74 | C75: Инженер | D75: Общество с ограниченной ответственностью "Томскнефтехим"/Направление Директора по производству/Производство полиэтилена/Смена 3 | E75: Инж смены | F75: СДП
A76: =IF(ISNA(INDEX('ID относящиеся у производству'!A:A,MATCH(B76,'ID относящиеся у производству'!A:A,0),1))=TRUE,"НЕТ","ДА") -> НЕТ | B76: 75 | C76: Мастер по ремонту | D76: Общество с ограниченной ответственностью "Томскнефтехим"/Направление Главного инженера/Направление заместителя главного инженера/Ремонтное производство/Ремонтное производство по ремонту технологических установок Производств: мономеров, полиэтилена, полипропилена/Участок по ремонту печей пиролиза/Поле
A77: =IF(ISNA(INDEX('ID относящиеся у производству'!A:A,MATCH(B77,'ID относящиеся у производству'!A:A,0),1))=TRUE,"НЕТ","ДА") -> НЕТ | B77: 76 | C77: Главный эксперт | D77: Общество с ограниченной ответственностью "Томскнефтехим"/Направление Главного инженера/Направление заместителя главного инженера/Служба управления основными фондами/Регионализация ФЭП КЦ/Центр компетенций Планирование и контроль
A78: =IF(ISNA(INDEX('ID относящиеся у производству'!A:A,MATCH(B78,'ID относящиеся у производству'!A:A,0),1))=TRUE,"НЕТ","ДА") -> НЕТ | B78: 77 | C78: Эксперт | D78: Общество с ограниченной ответственностью "Томскнефтехим"/Производственно-диспетчерское управление
A79: =IF(ISNA(INDEX('ID относящиеся у производству'!A:A,MATCH(B79,'ID относящиеся у производству'!A:A,0),1))=TRUE,"НЕТ","ДА") -> НЕТ | B79: 78 | C79: Мастер по ремонту технологического оборудования | D79: Общество с ограниченной ответственностью "Томскнефтехим"/Направление Главного инженера/Направление заместителя главного инженера/Ремонтное производство/Ремонтное производство по ремонту технологического оборудования Производств: мономеров, полиэтилена, полипропилена/Участок по ТОиР компрессорного и технологического оборудования ПМ, ППЭ, ППП, ПУиСП/Группа по оперативному ремонту технологического оборудования производств/Поле
A80: =IF(ISNA(INDEX('ID относящиеся у производству'!A:A,MATCH(B80,'ID относящиеся у производству'!A:A,0),1))=TRUE,"НЕТ","ДА") -> НЕТ | B80: 79 | C80: Главный эксперт | D80: Общество с ограниченной ответственностью "Томскнефтехим"/Направление Главного инженера/Направление заместителя главного инженера/Служба управления основными фондами/Технологическая независимость
A81: =IF(ISNA(INDEX('ID относящиеся у производству'!A:A,MATCH(B81,'ID относящиеся у производству'!A:A,0),1))=TRUE,"НЕТ","ДА") -> НЕТ | B81: 80 | C81: Менеджер | D81: Общество с ограниченной ответственностью "Томскнефтехим"/Направление Главного инженера/Проектный офис "Целевые инициативы"
A82: =IF(ISNA(INDEX('ID относящиеся у производству'!A:A,MATCH(B82,'ID относящиеся у производству'!A:A,0),1))=TRUE,"НЕТ","ДА") -> НЕТ | B82: 81 | C82: Ведущий инженер | D82: Общество с ограниченной ответственностью "Томскнефтехим"/Направление Главного инженера/Направление заместителя главного инженера/Ремонтное производство/Ремонтное производство по изготовлению
A83: =IF(ISNA(INDEX('ID относящиеся у производству'!A:A,MATCH(B83,'ID относящиеся у производству'!A:A,0),1))=TRUE,"НЕТ","ДА") -> НЕТ | B83: 82 | C83: Ведущий инженер-технолог | D83: Общество с ограниченной ответственностью "Томскнефтехим"/Служба главного технолога/Отдел технологии и развития
A84: =IF(ISNA(INDEX('ID относящиеся у производству'!A:A,MATCH(B84,'ID относящиеся у производству'!A:A,0),1))=TRUE,"НЕТ","ДА") -> НЕТ | B84: 83 | C84: Инженер-технолог | D84: Общество с ограниченной ответственностью "Томскнефтехим"/Направление Главного инженера/Направление заместителя главного инженера/Ремонтное производство/Ремонтное производство по изготовлению
A85: =IF(ISNA(INDEX('ID относящиеся у производству'!A:A,MATCH(B85,'ID относящиеся у производству'!A:A,0),1))=TRUE,"НЕТ","ДА") -> НЕТ | B85: 84 | C85: Ведущий специалист | D85: Общество с ограниченной ответственностью "Томскнефтехим"/Направление Главного инженера/Направление заместителя главного инженера/Ремонтное производство/Ремонтное производство по изготовлению
A86: =IF(ISNA(INDEX('ID относящиеся у производству'!A:A,MATCH(B86,'ID относящиеся у производству'!A:A,0),1))=TRUE,"НЕТ","ДА") -> НЕТ | B86: 85 | C86: Инженер-механик | D86: Общество с ограниченной ответственностью "Томскнефтехим"/Направление Главного инженера/Направление заместителя главного инженера/Служба управления основными фондами/Остановочные ремонты
A87: =IF(ISNA(INDEX('ID относящиеся у производству'!A:A,MATCH(B87,'ID относящиеся у производству'!A:A,0),1))=TRUE,"НЕТ","ДА") -> НЕТ | B87: 86 | C87: Руководитель ремонтного производства | D87: Общество с ограниченной ответственностью "Томскнефтехим"/Направление Главного инженера/Направление заместителя главного инженера/Ремонтное производство
... A89: =IF(ISNA(INDEX('ID относящиеся у производству'!A:A,MATCH(B89,'ID относящиеся у производству'!A:A,0),1))=TRUE,"НЕТ","ДА") -> НЕТ | B89: 88 | C89: Ведущий инженер | D89: Общество с ограниченной ответственностью "Томскнефтехим"/Направление Главного инженера/Служба управления надежностью/Отдел технического надзора
A90: =IF(ISNA(INDEX('ID относящиеся у производству'!A:A,MATCH(B90,'ID относящиеся у производству'!A:A,0),1))=TRUE,"НЕТ","ДА") -> ДА | B90: 89 | C90: Инженер | D90: Общество с ограниченной ответственностью "Томскнефтехим"/Направление Директора по производству/Производство мономеров/Смена 3/Установка пиролиза углеводородов нефти | E90: Инж смены | F90: СДП
A91: =IF(ISNA(INDEX('ID относящиеся у производству'!A:A,MATCH(B91,'ID относящиеся у производству'!A:A,0),1))=TRUE,"НЕТ","ДА") -> НЕТ | B91: 90 | C91: Ведущий инженер | D91: Общество с ограниченной ответственностью "Томскнефтехим"/Направление Главного инженера/Служба управления надежностью/Отдел технического надзора
A92: =IF(ISNA(INDEX('ID относящиеся у производству'!A:A,MATCH(B92,'ID относящиеся у производству'!A:A,0),1))=TRUE,"НЕТ","ДА") -> ДА | B92: 91 | C92: Начальник отдела | D92: Общество с ограниченной ответственностью "Томскнефтехим"/Направление Директора по производству/Отдел управления энергоресурсами
A93: =IF(ISNA(INDEX('ID относящиеся у производству'!A:A,MATCH(B93,'ID относящиеся у производству'!A:A,0),1))=TRUE,"НЕТ","ДА") -> ДА | B93: 92 | C93: Инженер | D93: Общество с ограниченной ответственностью "Томскнефтехим"/Направление Директора по производству/Производство полиэтилена/Смена 1 | E93: Инж смены | F93: СДП
A94: =IF(ISNA(INDEX('ID относящиеся у производству'!A:A,MATCH(B94,'ID относящиеся у производству'!A:A,0),1))=TRUE,"НЕТ","ДА") -> НЕТ | B94: 93 | C94: Начальник центральной заводской лаборатории | D94: Общество с ограниченной ответственностью "Томскнефтехим"/Служба главного технолога/Центральная заводская лаборатория
A95: =IF(ISNA(INDEX('ID относящиеся у производству'!A:A,MATCH(B95,'ID относящиеся у производству'!A:A,0),1))=TRUE,"НЕТ","ДА") -> НЕТ | B95: 94 | C95: Эксперт | D95: Общество с ограниченной ответственностью "Томскнефтехим"/Направление Главного инженера/Направление заместителя главного инженера/Ремонтное производство/Ремонтное производство по ремонту технологических установок Производств: мономеров, полиэтилена, полипропилена/Участок по ремонту технологических трубопроводов, трубопроводной арматуры и изготовлению нестандартного, котельного оборудования/Поле
A96: =IF(ISNA(INDEX('ID относящиеся у производству'!A:A,MATCH(B96,'ID относящиеся у производству'!A:A,0),1))=TRUE,"НЕТ","ДА") -> НЕТ | B96: 95 | C96: Руководитель службы | D96: Общество с ограниченной ответственностью "Томскнефтехим"/Направление Главного инженера/Служба управления надежностью
A97: =IF(ISNA(INDEX('ID относящиеся у производству'!A:A,MATCH(B97,'ID относящиеся у производству'!A:A,0),1))=TRUE,"НЕТ","ДА") -> НЕТ | B97: 96 | C97: Инженер-технолог | D97: Общество с ограниченной ответственностью "Томскнефтехим"/Служба главного технолога/Отдел качества, стандартизации и технического регулирования
A98: =IF(ISNA(INDEX('ID относящиеся у производству'!A:A,MATCH(B98,'ID относящиеся у производству'!A:A,0),1))=TRUE,"НЕТ","ДА") -> НЕТ | B98: 97 | C98: Ведущий инженер | D98: Общество с ограниченной ответственностью "Томскнефтехим"/Направление Главного инженера/Служба управления надежностью/Отдел технического надзора
A99: =IF(ISNA(INDEX('ID относящиеся у производству'!A:A,MATCH(B99,'ID относящиеся у производству'!A:A,0),1))=TRUE,"НЕТ","ДА") -> НЕТ | B99: 98 | C99: Инженер | D99: Общество с ограниченной ответственностью "Томскнефтехим"/Направление Главного инженера/Направление заместителя главного инженера/Ремонтное производство/Ремонтное производство по изготовлению/Отдел технического контроля
A100: =IF(ISNA(INDEX('ID относящиеся у производству'!A:A,MATCH(B100,'ID относящиеся у производству'!A:A,0),1))=TRUE,"НЕТ","ДА") -> ДА | B100: 99 | C100: Инженер | D100: Общество с ограниченной ответственностью "Томскнефтехим"/Направление Директора по производству/Производство мономеров/Смена 2/Установка компримирования и разделения пирогаза | E100: Инж смены | F100: СДП
A101: =IF(ISNA(INDEX('ID относящиеся у производству'!A:A,MATCH(B101,'ID относящиеся у производству'!A:A,0),1))=TRUE,"НЕТ","ДА") -> НЕТ | B101: 100 | C101: Инженер-механик | D101: Общество с ограниченной ответственностью "Томскнефтехим"/Направление Главного инженера/Направление заместителя главного инженера/Служба управления основными фондами/Отдел технического обслуживания и ремонтов/Техническое обслуживание и ремонты Производства полиэтилена
A102: =IF(ISNA(INDEX('ID относящиеся у производству'!A:A,MATCH(B102,'ID относящиеся у производству'!A:A,0),1))=TRUE,"НЕТ","ДА") -> НЕТ | B102: 101 | C102: Инженер-механик | D102: Общество с ограниченной ответственностью "Томскнефтехим"/Направление Главного инженера/Направление заместителя главного инженера/Служба управления основными фондами/Отдел технического обслуживания и ремонтов/Техническое обслуживание и ремонты Энергопроизводства
A103: =IF(ISNA(INDEX('ID относящиеся у производству'!A:A,MATCH(B103,'ID относящиеся у производству'!A:A,0),1))=TRUE,"НЕТ","ДА") -> НЕТ | B103: 102 | C103: Инженер по ресурсному планированию | D103: Общество с ограниченной ответственностью "Томскнефтехим"/Направление Главного инженера/Направление заместителя главного инженера/Служба управления основными фондами/Отдел технического обслуживания и ремонтов/Планирование
A104: =IF(ISNA(INDEX('ID относящиеся у производству'!A:A,MATCH(B104,'ID относящиеся у производству'!A:A,0),1))=TRUE,"НЕТ","ДА") -> НЕТ | B104: 103 | C104: Эксперт | D104: Общество с ограниченной ответственностью "Томскнефтехим"/Направление Главного инженера/Направление заместителя главного инженера/Ремонтное производство/Ремонтное производство по ремонту технологического оборудования Производств: мономеров, полиэтилена, полипропилена/Участок по ТОиР компрессорного и технологического оборудования ПМ, ППЭ, ППП, ПУиСП/Цех
A105: =IF(ISNA(INDEX('ID относящиеся у производству'!A:A,MATCH(B105,'ID относящиеся у производству'!A:A,0),1))=TRUE,"НЕТ","ДА") -> НЕТ | B105: 104 | C105: Главный эксперт | D105: Общество с ограниченной ответственностью "Томскнефтехим"/Направление Главного инженера/Служба управления надежностью/Направление Главного энергетика
A106: =IF(ISNA(INDEX('ID относящиеся у производству'!A:A,MATCH(B106,'ID относящиеся у производству'!A:A,0),1))=TRUE,"НЕТ","ДА") -> НЕТ | B106: 105 | C106: Специалист | D106: Общество с ограниченной ответственностью "Томскнефтехим"/Направление Главного инженера/Направление заместителя главного инженера/Управление материально-техническим обеспечением производства/Складское хозяйство
A107: =IF(ISNA(INDEX('ID относящиеся у производству'!A:A,MATCH(B107,'ID относящиеся у производству'!A:A,0),1))=TRUE,"НЕТ","ДА") -> НЕТ | B107: 106 | C107: Ведущий инженер-химик | D107: Общество с ограниченной ответственностью "Томскнефтехим"/Служба главного технолога/Центральная заводская лаборатория
A108: =IF(ISNA(INDEX('ID относящиеся у производству'!A:A,MATCH(B108,'ID относящиеся у производству'!A:A,0),1))=TRUE,"НЕТ","ДА") -> ДА | B108: 107 | C108: Инженер по подготовке производства | D108: Общество с ограниченной ответственностью "Томскнефтехим"/Направление Директора по производству/Энергопроизводство/Установка водоснабжения, канализации и оборотного водоснабжения | E108: ИПП | F108: СДП
A109: =IF(ISNA(INDEX('ID относящиеся у производству'!A:A,MATCH(B109,'ID относящиеся у производству'!A:A,0),1))=TRUE,"НЕТ","ДА") -> НЕТ | B109: 108 | C109: Эксперт | D109: Общество с ограниченной ответственностью "Томскнефтехим"/Направление Главного инженера/Направление заместителя главного инженера/Служба управления основными фондами/Отдел планирования и контроля
A110: =IF(ISNA(INDEX('ID относящиеся у производству'!A:A,MATCH(B110,'ID относящиеся у производству'!A:A,0),1))=TRUE,"НЕТ","ДА") -> НЕТ | B110: 109 | C110: Эксперт | D110: Общество с ограниченной ответственностью "Томскнефтехим"/Направление Главного инженера/Направление заместителя главного инженера/Служба управления основными фондами/Отдел планирования и контроля
...

Sheet ID относящиеся у производству
A1: 2
A2: 10
A3: 11
A4: 15
A5: 18
A6: 22
A7: 31
A8: 35
A9: 41
A10: 43
A11: 46
A12: 50
... A116: 542

Sheet ключи должностей к матрице
B2: СДП | O2: СГИ | AA2: СГТ и ЦЗЛ
B3: ДПП/ ДЗ | C3: МОК | D3: НП | E3: СМП | F3: 5НС | G3: ВИП | H3: Инж. по качеству | I3: ИПП | J3: ИПРО | K3: НС | L3: Инж смены | M3: Операторы пульта | N3: Операторы поля | O3: ГИ | P3: рук СУН | Q3: Работники СУН | R3: рук СУОФ | S3: рук ТОиР | T3: работники ТОиР | U3: рук РП | V3: НУ РП | W3: рем.персонал | X3: Рук ПО | Y3: РП ПО | Z3: рук ОР | AA3: ГТ | AB3: МТиР | AC3: ВИТ | AD3: ЭМ | AE3: МПП/ЭПП | AF3: МпоКачеству | AG3: Станарт | AH3: Эксперт по стандартизации | AI3: рук ЦЗЛ | AJ3: Химимки
B4: директор по производству | C4: менеджер по обеспечению компетенций | D4: начальник производства | E4: старший менеджер производства | F4: пятый начальник смены | G4: ведущий инженер производства | H4: инженер по качеству | I4: инженер по подготовке производства | J4: инженер по ресурсному обеспечению | K4: начальник смены | L4: инженер смены | O4: главный инженер | P4: рук службы управления надежнотью | Q4: принадлежность к службе упр надежностью | AA4: главный технолог | AC4: ведущий инеженер технолог | AD4: энергоменеджер
B5: директор завода
